{
    "date":"2019-06-25",
    "revisions":{
        "364251":{
            "clang-trunk-cortex-m0-Os":{
                "flags":[
                    "--target=arm-none-eabi",
                    "-Os",
                    "-mcpu=cortex-m0",
                    "-mthumb",
                    "-isysroot",
                    "/usr/lib/arm-none-eabi",
                    "-iwithsysroot",
                    "/include"
                ],
                "projects":{
                    "OpenTCP-1.0.4":25797,
                    "bzip2-1.0.2":53298,
                    "cg_compiler_opensrc":99038,
                    "compiler":21753,
                    "flex-2.5.31":195199,
                    "jikespg-1.3":176930,
                    "jpeg-6b":115413,
                    "libmspack":55581,
                    "libpng-1.2.5":86043,
                    "lwip-0.5.3.preproc":116126,
                    "mpeg2dec-0.3.1":40370,
                    "mpgcut-1.1":12344,
                    "replaypc-0.4.0.preproc":80077,
                    "teem-1.6.0-src":860813,
                    "ttt-0.10.1.preproc":28988,
                    "unrarlib-0.4.0":11809,
                    "zlib-1.1.4":31338
                },
                "sum":2010917
            },
            "clang-trunk-cortex-m0-Oz":{
                "flags":[
                    "--target=arm-none-eabi",
                    "-Oz",
                    "-mcpu=cortex-m0",
                    "-mthumb",
                    "-isysroot",
                    "/usr/lib/arm-none-eabi",
                    "-iwithsysroot",
                    "/include"
                ],
                "projects":{
                    "OpenTCP-1.0.4":23267,
                    "bzip2-1.0.2":47084,
                    "cg_compiler_opensrc":95692,
                    "compiler":20745,
                    "flex-2.5.31":189401,
                    "jikespg-1.3":168916,
                    "jpeg-6b":108795,
                    "libmspack":53503,
                    "libpng-1.2.5":83695,
                    "lwip-0.5.3.preproc":116126,
                    "mpeg2dec-0.3.1":39170,
                    "mpgcut-1.1":7384,
                    "replaypc-0.4.0.preproc":80077,
                    "teem-1.6.0-src":852393,
                    "ttt-0.10.1.preproc":28988,
                    "unrarlib-0.4.0":11249,
                    "zlib-1.1.4":31096
                },
                "sum":1957581
            },
            "clang-trunk-cortex-m4-Os":{
                "flags":[
                    "--target=arm-none-eabi",
                    "-Os",
                    "-mcpu=cortex-m4",
                    "-mthumb",
                    "-isysroot",
                    "/usr/lib/arm-none-eabi",
                    "-iwithsysroot",
                    "/include"
                ],
                "projects":{
                    "OpenTCP-1.0.4":27427,
                    "bzip2-1.0.2":55478,
                    "cg_compiler_opensrc":103614,
                    "compiler":23167,
                    "flex-2.5.31":211269,
                    "jikespg-1.3":209688,
                    "jpeg-6b":117117,
                    "libmspack":59265,
                    "libpng-1.2.5":90151,
                    "lwip-0.5.3.preproc":116126,
                    "mpeg2dec-0.3.1":42904,
                    "mpgcut-1.1":14500,
                    "replaypc-0.4.0.preproc":80077,
                    "teem-1.6.0-src":953761,
                    "ttt-0.10.1.preproc":28988,
                    "unrarlib-0.4.0":13401,
                    "zlib-1.1.4":32334
                },
                "sum":2179267
            },
            "clang-trunk-cortex-m4-Oz":{
                "flags":[
                    "--target=arm-none-eabi",
                    "-Oz",
                    "-mcpu=cortex-m4",
                    "-mthumb",
                    "-isysroot",
                    "/usr/lib/arm-none-eabi",
                    "-iwithsysroot",
                    "/include"
                ],
                "projects":{
                    "OpenTCP-1.0.4":23377,
                    "bzip2-1.0.2":46828,
                    "cg_compiler_opensrc":95248,
                    "compiler":20813,
                    "flex-2.5.31":191583,
                    "jikespg-1.3":173750,
                    "jpeg-6b":106437,
                    "libmspack":53093,
                    "libpng-1.2.5":84911,
                    "lwip-0.5.3.preproc":116126,
                    "mpeg2dec-0.3.1":40140,
                    "mpgcut-1.1":7844,
                    "replaypc-0.4.0.preproc":80077,
                    "teem-1.6.0-src":910637,
                    "ttt-0.10.1.preproc":28988,
                    "unrarlib-0.4.0":11413,
                    "zlib-1.1.4":29908
                },
                "sum":2021173
            },
            "clang-trunk-native-Os":{
                "flags":[
                    "-Os"
                ],
                "projects":{
                    "OpenTCP-1.0.4":37195,
                    "bzip2-1.0.2":70567,
                    "cg_compiler_opensrc":145726,
                    "compiler":29772,
                    "flex-2.5.31":217348,
                    "jikespg-1.3":228996,
                    "jpeg-6b":162758,
                    "libmspack":76133,
                    "libpng-1.2.5":120131,
                    "lwip-0.5.3.preproc":116126,
                    "mpeg2dec-0.3.1":64293,
                    "mpgcut-1.1":12248,
                    "replaypc-0.4.0.preproc":80077,
                    "teem-1.6.0-src":1014224,
                    "ttt-0.10.1.preproc":28988,
                    "unrarlib-0.4.0":15566,
                    "zlib-1.1.4":46017
                },
                "sum":2466165
            },
            "clang-trunk-native-Oz":{
                "flags":[
                    "-Oz"
                ],
                "projects":{
                    "OpenTCP-1.0.4":36366,
                    "bzip2-1.0.2":63664,
                    "cg_compiler_opensrc":143898,
                    "compiler":28232,
                    "flex-2.5.31":214266,
                    "jikespg-1.3":224412,
                    "jpeg-6b":155480,
                    "libmspack":75489,
                    "libpng-1.2.5":118909,
                    "lwip-0.5.3.preproc":116126,
                    "mpeg2dec-0.3.1":55005,
                    "mpgcut-1.1":9684,
                    "replaypc-0.4.0.preproc":80077,
                    "teem-1.6.0-src":1012990,
                    "ttt-0.10.1.preproc":28988,
                    "unrarlib-0.4.0":14901,
                    "zlib-1.1.4":46644
                },
                "sum":2425131
            }
        },
        "364256":{
            "clang-trunk-cortex-m0-Os":{
                "flags":[
                    "--target=arm-none-eabi",
                    "-Os",
                    "-mcpu=cortex-m0",
                    "-mthumb",
                    "-isysroot",
                    "/usr/lib/arm-none-eabi",
                    "-iwithsysroot",
                    "/include"
                ],
                "projects":{
                    "OpenTCP-1.0.4":25797,
                    "bzip2-1.0.2":53298,
                    "cg_compiler_opensrc":99038,
                    "compiler":21753,
                    "flex-2.5.31":195199,
                    "jikespg-1.3":176930,
                    "jpeg-6b":115413,
                    "libmspack":55581,
                    "libpng-1.2.5":86043,
                    "lwip-0.5.3.preproc":116126,
                    "mpeg2dec-0.3.1":40370,
                    "mpgcut-1.1":12344,
                    "replaypc-0.4.0.preproc":80077,
                    "teem-1.6.0-src":860813,
                    "ttt-0.10.1.preproc":28988,
                    "unrarlib-0.4.0":11809,
                    "zlib-1.1.4":31338
                },
                "sum":2010917
            },
            "clang-trunk-cortex-m0-Oz":{
                "flags":[
                    "--target=arm-none-eabi",
                    "-Oz",
                    "-mcpu=cortex-m0",
                    "-mthumb",
                    "-isysroot",
                    "/usr/lib/arm-none-eabi",
                    "-iwithsysroot",
                    "/include"
                ],
                "projects":{
                    "OpenTCP-1.0.4":23267,
                    "bzip2-1.0.2":47084,
                    "cg_compiler_opensrc":95692,
                    "compiler":20745,
                    "flex-2.5.31":189401,
                    "jikespg-1.3":168916,
                    "jpeg-6b":108795,
                    "libmspack":53503,
                    "libpng-1.2.5":83695,
                    "lwip-0.5.3.preproc":116126,
                    "mpeg2dec-0.3.1":39170,
                    "mpgcut-1.1":7384,
                    "replaypc-0.4.0.preproc":80077,
                    "teem-1.6.0-src":852393,
                    "ttt-0.10.1.preproc":28988,
                    "unrarlib-0.4.0":11249,
                    "zlib-1.1.4":31096
                },
                "sum":1957581
            },
            "clang-trunk-cortex-m4-Os":{
                "flags":[
                    "--target=arm-none-eabi",
                    "-Os",
                    "-mcpu=cortex-m4",
                    "-mthumb",
                    "-isysroot",
                    "/usr/lib/arm-none-eabi",
                    "-iwithsysroot",
                    "/include"
                ],
                "projects":{
                    "OpenTCP-1.0.4":27427,
                    "bzip2-1.0.2":55478,
                    "cg_compiler_opensrc":103614,
                    "compiler":23167,
                    "flex-2.5.31":211269,
                    "jikespg-1.3":209688,
                    "jpeg-6b":117117,
                    "libmspack":59265,
                    "libpng-1.2.5":90151,
                    "lwip-0.5.3.preproc":116126,
                    "mpeg2dec-0.3.1":42904,
                    "mpgcut-1.1":14500,
                    "replaypc-0.4.0.preproc":80077,
                    "teem-1.6.0-src":953761,
                    "ttt-0.10.1.preproc":28988,
                    "unrarlib-0.4.0":13401,
                    "zlib-1.1.4":32334
                },
                "sum":2179267
            },
            "clang-trunk-cortex-m4-Oz":{
                "flags":[
                    "--target=arm-none-eabi",
                    "-Oz",
                    "-mcpu=cortex-m4",
                    "-mthumb",
                    "-isysroot",
                    "/usr/lib/arm-none-eabi",
                    "-iwithsysroot",
                    "/include"
                ],
                "projects":{
                    "OpenTCP-1.0.4":23377,
                    "bzip2-1.0.2":46828,
                    "cg_compiler_opensrc":95248,
                    "compiler":20813,
                    "flex-2.5.31":191583,
                    "jikespg-1.3":173750,
                    "jpeg-6b":106437,
                    "libmspack":53093,
                    "libpng-1.2.5":84911,
                    "lwip-0.5.3.preproc":116126,
                    "mpeg2dec-0.3.1":40140,
                    "mpgcut-1.1":7844,
                    "replaypc-0.4.0.preproc":80077,
                    "teem-1.6.0-src":910637,
                    "ttt-0.10.1.preproc":28988,
                    "unrarlib-0.4.0":11413,
                    "zlib-1.1.4":29908
                },
                "sum":2021173
            },
            "clang-trunk-native-Os":{
                "flags":[
                    "-Os"
                ],
                "projects":{
                    "OpenTCP-1.0.4":37195,
                    "bzip2-1.0.2":70567,
                    "cg_compiler_opensrc":145726,
                    "compiler":29772,
                    "flex-2.5.31":217348,
                    "jikespg-1.3":228996,
                    "jpeg-6b":162758,
                    "libmspack":76133,
                    "libpng-1.2.5":120131,
                    "lwip-0.5.3.preproc":116126,
                    "mpeg2dec-0.3.1":64293,
                    "mpgcut-1.1":12248,
                    "replaypc-0.4.0.preproc":80077,
                    "teem-1.6.0-src":1014224,
                    "ttt-0.10.1.preproc":28988,
                    "unrarlib-0.4.0":15566,
                    "zlib-1.1.4":46017
                },
                "sum":2466165
            },
            "clang-trunk-native-Oz":{
                "flags":[
                    "-Oz"
                ],
                "projects":{
                    "OpenTCP-1.0.4":36366,
                    "bzip2-1.0.2":63664,
                    "cg_compiler_opensrc":143898,
                    "compiler":28232,
                    "flex-2.5.31":214266,
                    "jikespg-1.3":224412,
                    "jpeg-6b":155480,
                    "libmspack":75489,
                    "libpng-1.2.5":118909,
                    "lwip-0.5.3.preproc":116126,
                    "mpeg2dec-0.3.1":55005,
                    "mpgcut-1.1":9684,
                    "replaypc-0.4.0.preproc":80077,
                    "teem-1.6.0-src":1012990,
                    "ttt-0.10.1.preproc":28988,
                    "unrarlib-0.4.0":14901,
                    "zlib-1.1.4":46644
                },
                "sum":2425131
            }
        },
        "364259":{
            "clang-trunk-cortex-m0-Os":{
                "flags":[
                    "--target=arm-none-eabi",
                    "-Os",
                    "-mcpu=cortex-m0",
                    "-mthumb",
                    "-isysroot",
                    "/usr/lib/arm-none-eabi",
                    "-iwithsysroot",
                    "/include"
                ],
                "projects":{
                    "OpenTCP-1.0.4":25797,
                    "bzip2-1.0.2":53298,
                    "cg_compiler_opensrc":99038,
                    "compiler":21753,
                    "flex-2.5.31":195199,
                    "jikespg-1.3":176930,
                    "jpeg-6b":115413,
                    "libmspack":55581,
                    "libpng-1.2.5":86043,
                    "lwip-0.5.3.preproc":116126,
                    "mpeg2dec-0.3.1":40370,
                    "mpgcut-1.1":12344,
                    "replaypc-0.4.0.preproc":80077,
                    "teem-1.6.0-src":860813,
                    "ttt-0.10.1.preproc":28988,
                    "unrarlib-0.4.0":11809,
                    "zlib-1.1.4":31338
                },
                "sum":2010917
            },
            "clang-trunk-cortex-m0-Oz":{
                "flags":[
                    "--target=arm-none-eabi",
                    "-Oz",
                    "-mcpu=cortex-m0",
                    "-mthumb",
                    "-isysroot",
                    "/usr/lib/arm-none-eabi",
                    "-iwithsysroot",
                    "/include"
                ],
                "projects":{
                    "OpenTCP-1.0.4":23267,
                    "bzip2-1.0.2":47084,
                    "cg_compiler_opensrc":95692,
                    "compiler":20745,
                    "flex-2.5.31":189401,
                    "jikespg-1.3":168916,
                    "jpeg-6b":108795,
                    "libmspack":53503,
                    "libpng-1.2.5":83695,
                    "lwip-0.5.3.preproc":116126,
                    "mpeg2dec-0.3.1":39170,
                    "mpgcut-1.1":7384,
                    "replaypc-0.4.0.preproc":80077,
                    "teem-1.6.0-src":852393,
                    "ttt-0.10.1.preproc":28988,
                    "unrarlib-0.4.0":11249,
                    "zlib-1.1.4":31096
                },
                "sum":1957581
            },
            "clang-trunk-cortex-m4-Os":{
                "flags":[
                    "--target=arm-none-eabi",
                    "-Os",
                    "-mcpu=cortex-m4",
                    "-mthumb",
                    "-isysroot",
                    "/usr/lib/arm-none-eabi",
                    "-iwithsysroot",
                    "/include"
                ],
                "projects":{
                    "OpenTCP-1.0.4":27427,
                    "bzip2-1.0.2":55478,
                    "cg_compiler_opensrc":103614,
                    "compiler":23167,
                    "flex-2.5.31":211269,
                    "jikespg-1.3":209688,
                    "jpeg-6b":117117,
                    "libmspack":59265,
                    "libpng-1.2.5":90151,
                    "lwip-0.5.3.preproc":116126,
                    "mpeg2dec-0.3.1":42904,
                    "mpgcut-1.1":14500,
                    "replaypc-0.4.0.preproc":80077,
                    "teem-1.6.0-src":953761,
                    "ttt-0.10.1.preproc":28988,
                    "unrarlib-0.4.0":13401,
                    "zlib-1.1.4":32334
                },
                "sum":2179267
            },
            "clang-trunk-cortex-m4-Oz":{
                "flags":[
                    "--target=arm-none-eabi",
                    "-Oz",
                    "-mcpu=cortex-m4",
                    "-mthumb",
                    "-isysroot",
                    "/usr/lib/arm-none-eabi",
                    "-iwithsysroot",
                    "/include"
                ],
                "projects":{
                    "OpenTCP-1.0.4":23377,
                    "bzip2-1.0.2":46828,
                    "cg_compiler_opensrc":95248,
                    "compiler":20813,
                    "flex-2.5.31":191583,
                    "jikespg-1.3":173750,
                    "jpeg-6b":106437,
                    "libmspack":53093,
                    "libpng-1.2.5":84911,
                    "lwip-0.5.3.preproc":116126,
                    "mpeg2dec-0.3.1":40140,
                    "mpgcut-1.1":7844,
                    "replaypc-0.4.0.preproc":80077,
                    "teem-1.6.0-src":910637,
                    "ttt-0.10.1.preproc":28988,
                    "unrarlib-0.4.0":11413,
                    "zlib-1.1.4":29908
                },
                "sum":2021173
            },
            "clang-trunk-native-Os":{
                "flags":[
                    "-Os"
                ],
                "projects":{
                    "OpenTCP-1.0.4":37195,
                    "bzip2-1.0.2":70567,
                    "cg_compiler_opensrc":145726,
                    "compiler":29772,
                    "flex-2.5.31":217348,
                    "jikespg-1.3":228996,
                    "jpeg-6b":162758,
                    "libmspack":76133,
                    "libpng-1.2.5":120131,
                    "lwip-0.5.3.preproc":116126,
                    "mpeg2dec-0.3.1":64293,
                    "mpgcut-1.1":12248,
                    "replaypc-0.4.0.preproc":80077,
                    "teem-1.6.0-src":1014224,
                    "ttt-0.10.1.preproc":28988,
                    "unrarlib-0.4.0":15566,
                    "zlib-1.1.4":46017
                },
                "sum":2466165
            },
            "clang-trunk-native-Oz":{
                "flags":[
                    "-Oz"
                ],
                "projects":{
                    "OpenTCP-1.0.4":36366,
                    "bzip2-1.0.2":63664,
                    "cg_compiler_opensrc":143898,
                    "compiler":28232,
                    "flex-2.5.31":214266,
                    "jikespg-1.3":224412,
                    "jpeg-6b":155480,
                    "libmspack":75489,
                    "libpng-1.2.5":118909,
                    "lwip-0.5.3.preproc":116126,
                    "mpeg2dec-0.3.1":55005,
                    "mpgcut-1.1":9684,
                    "replaypc-0.4.0.preproc":80077,
                    "teem-1.6.0-src":1012990,
                    "ttt-0.10.1.preproc":28988,
                    "unrarlib-0.4.0":14901,
                    "zlib-1.1.4":46644
                },
                "sum":2425131
            }
        },
        "364263":{
            "clang-trunk-cortex-m0-Os":{
                "flags":[
                    "--target=arm-none-eabi",
                    "-Os",
                    "-mcpu=cortex-m0",
                    "-mthumb",
                    "-isysroot",
                    "/usr/lib/arm-none-eabi",
                    "-iwithsysroot",
                    "/include"
                ],
                "projects":{
                    "OpenTCP-1.0.4":25797,
                    "bzip2-1.0.2":53298,
                    "cg_compiler_opensrc":99038,
                    "compiler":21753,
                    "flex-2.5.31":195199,
                    "jikespg-1.3":176930,
                    "jpeg-6b":115413,
                    "libmspack":55581,
                    "libpng-1.2.5":86043,
                    "lwip-0.5.3.preproc":116126,
                    "mpeg2dec-0.3.1":40370,
                    "mpgcut-1.1":12344,
                    "replaypc-0.4.0.preproc":80077,
                    "teem-1.6.0-src":860813,
                    "ttt-0.10.1.preproc":28988,
                    "unrarlib-0.4.0":11809,
                    "zlib-1.1.4":31338
                },
                "sum":2010917
            },
            "clang-trunk-cortex-m0-Oz":{
                "flags":[
                    "--target=arm-none-eabi",
                    "-Oz",
                    "-mcpu=cortex-m0",
                    "-mthumb",
                    "-isysroot",
                    "/usr/lib/arm-none-eabi",
                    "-iwithsysroot",
                    "/include"
                ],
                "projects":{
                    "OpenTCP-1.0.4":23267,
                    "bzip2-1.0.2":47084,
                    "cg_compiler_opensrc":95692,
                    "compiler":20745,
                    "flex-2.5.31":189401,
                    "jikespg-1.3":168916,
                    "jpeg-6b":108795,
                    "libmspack":53503,
                    "libpng-1.2.5":83695,
                    "lwip-0.5.3.preproc":116126,
                    "mpeg2dec-0.3.1":39170,
                    "mpgcut-1.1":7384,
                    "replaypc-0.4.0.preproc":80077,
                    "teem-1.6.0-src":852393,
                    "ttt-0.10.1.preproc":28988,
                    "unrarlib-0.4.0":11249,
                    "zlib-1.1.4":31096
                },
                "sum":1957581
            },
            "clang-trunk-cortex-m4-Os":{
                "flags":[
                    "--target=arm-none-eabi",
                    "-Os",
                    "-mcpu=cortex-m4",
                    "-mthumb",
                    "-isysroot",
                    "/usr/lib/arm-none-eabi",
                    "-iwithsysroot",
                    "/include"
                ],
                "projects":{
                    "OpenTCP-1.0.4":27427,
                    "bzip2-1.0.2":55478,
                    "cg_compiler_opensrc":103614,
                    "compiler":23167,
                    "flex-2.5.31":211269,
                    "jikespg-1.3":209688,
                    "jpeg-6b":117117,
                    "libmspack":59265,
                    "libpng-1.2.5":90151,
                    "lwip-0.5.3.preproc":116126,
                    "mpeg2dec-0.3.1":42904,
                    "mpgcut-1.1":14500,
                    "replaypc-0.4.0.preproc":80077,
                    "teem-1.6.0-src":953761,
                    "ttt-0.10.1.preproc":28988,
                    "unrarlib-0.4.0":13401,
                    "zlib-1.1.4":32334
                },
                "sum":2179267
            },
            "clang-trunk-cortex-m4-Oz":{
                "flags":[
                    "--target=arm-none-eabi",
                    "-Oz",
                    "-mcpu=cortex-m4",
                    "-mthumb",
                    "-isysroot",
                    "/usr/lib/arm-none-eabi",
                    "-iwithsysroot",
                    "/include"
                ],
                "projects":{
                    "OpenTCP-1.0.4":23377,
                    "bzip2-1.0.2":46828,
                    "cg_compiler_opensrc":95248,
                    "compiler":20813,
                    "flex-2.5.31":191583,
                    "jikespg-1.3":173750,
                    "jpeg-6b":106437,
                    "libmspack":53093,
                    "libpng-1.2.5":84911,
                    "lwip-0.5.3.preproc":116126,
                    "mpeg2dec-0.3.1":40140,
                    "mpgcut-1.1":7844,
                    "replaypc-0.4.0.preproc":80077,
                    "teem-1.6.0-src":910637,
                    "ttt-0.10.1.preproc":28988,
                    "unrarlib-0.4.0":11413,
                    "zlib-1.1.4":29908
                },
                "sum":2021173
            },
            "clang-trunk-native-Os":{
                "flags":[
                    "-Os"
                ],
                "projects":{
                    "OpenTCP-1.0.4":37195,
                    "bzip2-1.0.2":70567,
                    "cg_compiler_opensrc":145726,
                    "compiler":29772,
                    "flex-2.5.31":217348,
                    "jikespg-1.3":228996,
                    "jpeg-6b":162758,
                    "libmspack":76133,
                    "libpng-1.2.5":120131,
                    "lwip-0.5.3.preproc":116126,
                    "mpeg2dec-0.3.1":64293,
                    "mpgcut-1.1":12248,
                    "replaypc-0.4.0.preproc":80077,
                    "teem-1.6.0-src":1014224,
                    "ttt-0.10.1.preproc":28988,
                    "unrarlib-0.4.0":15566,
                    "zlib-1.1.4":46017
                },
                "sum":2466165
            },
            "clang-trunk-native-Oz":{
                "flags":[
                    "-Oz"
                ],
                "projects":{
                    "OpenTCP-1.0.4":36366,
                    "bzip2-1.0.2":63664,
                    "cg_compiler_opensrc":143898,
                    "compiler":28232,
                    "flex-2.5.31":214266,
                    "jikespg-1.3":224412,
                    "jpeg-6b":155480,
                    "libmspack":75489,
                    "libpng-1.2.5":118909,
                    "lwip-0.5.3.preproc":116126,
                    "mpeg2dec-0.3.1":55005,
                    "mpgcut-1.1":9684,
                    "replaypc-0.4.0.preproc":80077,
                    "teem-1.6.0-src":1012990,
                    "ttt-0.10.1.preproc":28988,
                    "unrarlib-0.4.0":14901,
                    "zlib-1.1.4":46644
                },
                "sum":2425131
            }
        },
        "364264":{
            "clang-trunk-cortex-m0-Os":{
                "flags":[
                    "--target=arm-none-eabi",
                    "-Os",
                    "-mcpu=cortex-m0",
                    "-mthumb",
                    "-isysroot",
                    "/usr/lib/arm-none-eabi",
                    "-iwithsysroot",
                    "/include"
                ],
                "projects":{
                    "OpenTCP-1.0.4":25797,
                    "bzip2-1.0.2":53298,
                    "cg_compiler_opensrc":99038,
                    "compiler":21753,
                    "flex-2.5.31":195199,
                    "jikespg-1.3":176930,
                    "jpeg-6b":115413,
                    "libmspack":55581,
                    "libpng-1.2.5":86043,
                    "lwip-0.5.3.preproc":116126,
                    "mpeg2dec-0.3.1":40370,
                    "mpgcut-1.1":12344,
                    "replaypc-0.4.0.preproc":80077,
                    "teem-1.6.0-src":860813,
                    "ttt-0.10.1.preproc":28988,
                    "unrarlib-0.4.0":11809,
                    "zlib-1.1.4":31338
                },
                "sum":2010917
            },
            "clang-trunk-cortex-m0-Oz":{
                "flags":[
                    "--target=arm-none-eabi",
                    "-Oz",
                    "-mcpu=cortex-m0",
                    "-mthumb",
                    "-isysroot",
                    "/usr/lib/arm-none-eabi",
                    "-iwithsysroot",
                    "/include"
                ],
                "projects":{
                    "OpenTCP-1.0.4":23267,
                    "bzip2-1.0.2":47084,
                    "cg_compiler_opensrc":95692,
                    "compiler":20745,
                    "flex-2.5.31":189401,
                    "jikespg-1.3":168916,
                    "jpeg-6b":108795,
                    "libmspack":53503,
                    "libpng-1.2.5":83695,
                    "lwip-0.5.3.preproc":116126,
                    "mpeg2dec-0.3.1":39170,
                    "mpgcut-1.1":7384,
                    "replaypc-0.4.0.preproc":80077,
                    "teem-1.6.0-src":852393,
                    "ttt-0.10.1.preproc":28988,
                    "unrarlib-0.4.0":11249,
                    "zlib-1.1.4":31096
                },
                "sum":1957581
            },
            "clang-trunk-cortex-m4-Os":{
                "flags":[
                    "--target=arm-none-eabi",
                    "-Os",
                    "-mcpu=cortex-m4",
                    "-mthumb",
                    "-isysroot",
                    "/usr/lib/arm-none-eabi",
                    "-iwithsysroot",
                    "/include"
                ],
                "projects":{
                    "OpenTCP-1.0.4":27427,
                    "bzip2-1.0.2":55478,
                    "cg_compiler_opensrc":103614,
                    "compiler":23167,
                    "flex-2.5.31":211269,
                    "jikespg-1.3":209688,
                    "jpeg-6b":117117,
                    "libmspack":59265,
                    "libpng-1.2.5":90151,
                    "lwip-0.5.3.preproc":116126,
                    "mpeg2dec-0.3.1":42904,
                    "mpgcut-1.1":14500,
                    "replaypc-0.4.0.preproc":80077,
                    "teem-1.6.0-src":953761,
                    "ttt-0.10.1.preproc":28988,
                    "unrarlib-0.4.0":13401,
                    "zlib-1.1.4":32334
                },
                "sum":2179267
            },
            "clang-trunk-cortex-m4-Oz":{
                "flags":[
                    "--target=arm-none-eabi",
                    "-Oz",
                    "-mcpu=cortex-m4",
                    "-mthumb",
                    "-isysroot",
                    "/usr/lib/arm-none-eabi",
                    "-iwithsysroot",
                    "/include"
                ],
                "projects":{
                    "OpenTCP-1.0.4":23377,
                    "bzip2-1.0.2":46828,
                    "cg_compiler_opensrc":95248,
                    "compiler":20813,
                    "flex-2.5.31":191583,
                    "jikespg-1.3":173750,
                    "jpeg-6b":106437,
                    "libmspack":53093,
                    "libpng-1.2.5":84911,
                    "lwip-0.5.3.preproc":116126,
                    "mpeg2dec-0.3.1":40140,
                    "mpgcut-1.1":7844,
                    "replaypc-0.4.0.preproc":80077,
                    "teem-1.6.0-src":910637,
                    "ttt-0.10.1.preproc":28988,
                    "unrarlib-0.4.0":11413,
                    "zlib-1.1.4":29908
                },
                "sum":2021173
            },
            "clang-trunk-native-Os":{
                "flags":[
                    "-Os"
                ],
                "projects":{
                    "OpenTCP-1.0.4":37195,
                    "bzip2-1.0.2":70567,
                    "cg_compiler_opensrc":145726,
                    "compiler":29772,
                    "flex-2.5.31":217348,
                    "jikespg-1.3":228996,
                    "jpeg-6b":162758,
                    "libmspack":76133,
                    "libpng-1.2.5":120131,
                    "lwip-0.5.3.preproc":116126,
                    "mpeg2dec-0.3.1":64293,
                    "mpgcut-1.1":12248,
                    "replaypc-0.4.0.preproc":80077,
                    "teem-1.6.0-src":1014224,
                    "ttt-0.10.1.preproc":28988,
                    "unrarlib-0.4.0":15566,
                    "zlib-1.1.4":46017
                },
                "sum":2466165
            },
            "clang-trunk-native-Oz":{
                "flags":[
                    "-Oz"
                ],
                "projects":{
                    "OpenTCP-1.0.4":36366,
                    "bzip2-1.0.2":63664,
                    "cg_compiler_opensrc":143898,
                    "compiler":28232,
                    "flex-2.5.31":214266,
                    "jikespg-1.3":224412,
                    "jpeg-6b":155480,
                    "libmspack":75489,
                    "libpng-1.2.5":118909,
                    "lwip-0.5.3.preproc":116126,
                    "mpeg2dec-0.3.1":55005,
                    "mpgcut-1.1":9684,
                    "replaypc-0.4.0.preproc":80077,
                    "teem-1.6.0-src":1012990,
                    "ttt-0.10.1.preproc":28988,
                    "unrarlib-0.4.0":14901,
                    "zlib-1.1.4":46644
                },
                "sum":2425131
            }
        },
        "364265":{
            "clang-trunk-cortex-m0-Os":{
                "flags":[
                    "--target=arm-none-eabi",
                    "-Os",
                    "-mcpu=cortex-m0",
                    "-mthumb",
                    "-isysroot",
                    "/usr/lib/arm-none-eabi",
                    "-iwithsysroot",
                    "/include"
                ],
                "projects":{
                    "OpenTCP-1.0.4":25797,
                    "bzip2-1.0.2":53298,
                    "cg_compiler_opensrc":99038,
                    "compiler":21753,
                    "flex-2.5.31":195199,
                    "jikespg-1.3":176930,
                    "jpeg-6b":115413,
                    "libmspack":55581,
                    "libpng-1.2.5":86043,
                    "lwip-0.5.3.preproc":116126,
                    "mpeg2dec-0.3.1":40370,
                    "mpgcut-1.1":12344,
                    "replaypc-0.4.0.preproc":80077,
                    "teem-1.6.0-src":860813,
                    "ttt-0.10.1.preproc":28988,
                    "unrarlib-0.4.0":11809,
                    "zlib-1.1.4":31338
                },
                "sum":2010917
            },
            "clang-trunk-cortex-m0-Oz":{
                "flags":[
                    "--target=arm-none-eabi",
                    "-Oz",
                    "-mcpu=cortex-m0",
                    "-mthumb",
                    "-isysroot",
                    "/usr/lib/arm-none-eabi",
                    "-iwithsysroot",
                    "/include"
                ],
                "projects":{
                    "OpenTCP-1.0.4":23267,
                    "bzip2-1.0.2":47084,
                    "cg_compiler_opensrc":95692,
                    "compiler":20745,
                    "flex-2.5.31":189401,
                    "jikespg-1.3":168916,
                    "jpeg-6b":108795,
                    "libmspack":53503,
                    "libpng-1.2.5":83695,
                    "lwip-0.5.3.preproc":116126,
                    "mpeg2dec-0.3.1":39170,
                    "mpgcut-1.1":7384,
                    "replaypc-0.4.0.preproc":80077,
                    "teem-1.6.0-src":852393,
                    "ttt-0.10.1.preproc":28988,
                    "unrarlib-0.4.0":11249,
                    "zlib-1.1.4":31096
                },
                "sum":1957581
            },
            "clang-trunk-cortex-m4-Os":{
                "flags":[
                    "--target=arm-none-eabi",
                    "-Os",
                    "-mcpu=cortex-m4",
                    "-mthumb",
                    "-isysroot",
                    "/usr/lib/arm-none-eabi",
                    "-iwithsysroot",
                    "/include"
                ],
                "projects":{
                    "OpenTCP-1.0.4":27427,
                    "bzip2-1.0.2":55478,
                    "cg_compiler_opensrc":103614,
                    "compiler":23167,
                    "flex-2.5.31":211269,
                    "jikespg-1.3":209688,
                    "jpeg-6b":117117,
                    "libmspack":59265,
                    "libpng-1.2.5":90151,
                    "lwip-0.5.3.preproc":116126,
                    "mpeg2dec-0.3.1":42904,
                    "mpgcut-1.1":14500,
                    "replaypc-0.4.0.preproc":80077,
                    "teem-1.6.0-src":953761,
                    "ttt-0.10.1.preproc":28988,
                    "unrarlib-0.4.0":13401,
                    "zlib-1.1.4":32334
                },
                "sum":2179267
            },
            "clang-trunk-cortex-m4-Oz":{
                "flags":[
                    "--target=arm-none-eabi",
                    "-Oz",
                    "-mcpu=cortex-m4",
                    "-mthumb",
                    "-isysroot",
                    "/usr/lib/arm-none-eabi",
                    "-iwithsysroot",
                    "/include"
                ],
                "projects":{
                    "OpenTCP-1.0.4":23377,
                    "bzip2-1.0.2":46828,
                    "cg_compiler_opensrc":95248,
                    "compiler":20813,
                    "flex-2.5.31":191583,
                    "jikespg-1.3":173750,
                    "jpeg-6b":106437,
                    "libmspack":53093,
                    "libpng-1.2.5":84911,
                    "lwip-0.5.3.preproc":116126,
                    "mpeg2dec-0.3.1":40140,
                    "mpgcut-1.1":7844,
                    "replaypc-0.4.0.preproc":80077,
                    "teem-1.6.0-src":910637,
                    "ttt-0.10.1.preproc":28988,
                    "unrarlib-0.4.0":11413,
                    "zlib-1.1.4":29908
                },
                "sum":2021173
            },
            "clang-trunk-native-Os":{
                "flags":[
                    "-Os"
                ],
                "projects":{
                    "OpenTCP-1.0.4":37195,
                    "bzip2-1.0.2":70567,
                    "cg_compiler_opensrc":145726,
                    "compiler":29772,
                    "flex-2.5.31":217348,
                    "jikespg-1.3":228996,
                    "jpeg-6b":162758,
                    "libmspack":76133,
                    "libpng-1.2.5":120131,
                    "lwip-0.5.3.preproc":116126,
                    "mpeg2dec-0.3.1":64293,
                    "mpgcut-1.1":12248,
                    "replaypc-0.4.0.preproc":80077,
                    "teem-1.6.0-src":1014224,
                    "ttt-0.10.1.preproc":28988,
                    "unrarlib-0.4.0":15566,
                    "zlib-1.1.4":46017
                },
                "sum":2466165
            },
            "clang-trunk-native-Oz":{
                "flags":[
                    "-Oz"
                ],
                "projects":{
                    "OpenTCP-1.0.4":36366,
                    "bzip2-1.0.2":63664,
                    "cg_compiler_opensrc":143898,
                    "compiler":28232,
                    "flex-2.5.31":214266,
                    "jikespg-1.3":224412,
                    "jpeg-6b":155480,
                    "libmspack":75489,
                    "libpng-1.2.5":118909,
                    "lwip-0.5.3.preproc":116126,
                    "mpeg2dec-0.3.1":55005,
                    "mpgcut-1.1":9684,
                    "replaypc-0.4.0.preproc":80077,
                    "teem-1.6.0-src":1012990,
                    "ttt-0.10.1.preproc":28988,
                    "unrarlib-0.4.0":14901,
                    "zlib-1.1.4":46644
                },
                "sum":2425131
            }
        },
        "364269":{
            "clang-trunk-cortex-m0-Os":{
                "flags":[
                    "--target=arm-none-eabi",
                    "-Os",
                    "-mcpu=cortex-m0",
                    "-mthumb",
                    "-isysroot",
                    "/usr/lib/arm-none-eabi",
                    "-iwithsysroot",
                    "/include"
                ],
                "projects":{
                    "OpenTCP-1.0.4":25797,
                    "bzip2-1.0.2":53298,
                    "cg_compiler_opensrc":99038,
                    "compiler":21753,
                    "flex-2.5.31":195199,
                    "jikespg-1.3":176930,
                    "jpeg-6b":115413,
                    "libmspack":55581,
                    "libpng-1.2.5":86043,
                    "lwip-0.5.3.preproc":116126,
                    "mpeg2dec-0.3.1":40370,
                    "mpgcut-1.1":12344,
                    "replaypc-0.4.0.preproc":80077,
                    "teem-1.6.0-src":860813,
                    "ttt-0.10.1.preproc":28988,
                    "unrarlib-0.4.0":11809,
                    "zlib-1.1.4":31338
                },
                "sum":2010917
            },
            "clang-trunk-cortex-m0-Oz":{
                "flags":[
                    "--target=arm-none-eabi",
                    "-Oz",
                    "-mcpu=cortex-m0",
                    "-mthumb",
                    "-isysroot",
                    "/usr/lib/arm-none-eabi",
                    "-iwithsysroot",
                    "/include"
                ],
                "projects":{
                    "OpenTCP-1.0.4":23267,
                    "bzip2-1.0.2":47084,
                    "cg_compiler_opensrc":95692,
                    "compiler":20745,
                    "flex-2.5.31":189401,
                    "jikespg-1.3":168916,
                    "jpeg-6b":108795,
                    "libmspack":53503,
                    "libpng-1.2.5":83695,
                    "lwip-0.5.3.preproc":116126,
                    "mpeg2dec-0.3.1":39170,
                    "mpgcut-1.1":7384,
                    "replaypc-0.4.0.preproc":80077,
                    "teem-1.6.0-src":852393,
                    "ttt-0.10.1.preproc":28988,
                    "unrarlib-0.4.0":11249,
                    "zlib-1.1.4":31096
                },
                "sum":1957581
            },
            "clang-trunk-cortex-m4-Os":{
                "flags":[
                    "--target=arm-none-eabi",
                    "-Os",
                    "-mcpu=cortex-m4",
                    "-mthumb",
                    "-isysroot",
                    "/usr/lib/arm-none-eabi",
                    "-iwithsysroot",
                    "/include"
                ],
                "projects":{
                    "OpenTCP-1.0.4":27427,
                    "bzip2-1.0.2":55478,
                    "cg_compiler_opensrc":103614,
                    "compiler":23167,
                    "flex-2.5.31":211269,
                    "jikespg-1.3":209688,
                    "jpeg-6b":117117,
                    "libmspack":59265,
                    "libpng-1.2.5":90151,
                    "lwip-0.5.3.preproc":116126,
                    "mpeg2dec-0.3.1":42904,
                    "mpgcut-1.1":14500,
                    "replaypc-0.4.0.preproc":80077,
                    "teem-1.6.0-src":953761,
                    "ttt-0.10.1.preproc":28988,
                    "unrarlib-0.4.0":13401,
                    "zlib-1.1.4":32334
                },
                "sum":2179267
            },
            "clang-trunk-cortex-m4-Oz":{
                "flags":[
                    "--target=arm-none-eabi",
                    "-Oz",
                    "-mcpu=cortex-m4",
                    "-mthumb",
                    "-isysroot",
                    "/usr/lib/arm-none-eabi",
                    "-iwithsysroot",
                    "/include"
                ],
                "projects":{
                    "OpenTCP-1.0.4":23377,
                    "bzip2-1.0.2":46828,
                    "cg_compiler_opensrc":95248,
                    "compiler":20813,
                    "flex-2.5.31":191583,
                    "jikespg-1.3":173750,
                    "jpeg-6b":106437,
                    "libmspack":53093,
                    "libpng-1.2.5":84911,
                    "lwip-0.5.3.preproc":116126,
                    "mpeg2dec-0.3.1":40140,
                    "mpgcut-1.1":7844,
                    "replaypc-0.4.0.preproc":80077,
                    "teem-1.6.0-src":910637,
                    "ttt-0.10.1.preproc":28988,
                    "unrarlib-0.4.0":11413,
                    "zlib-1.1.4":29908
                },
                "sum":2021173
            },
            "clang-trunk-native-Os":{
                "flags":[
                    "-Os"
                ],
                "projects":{
                    "OpenTCP-1.0.4":37195,
                    "bzip2-1.0.2":70567,
                    "cg_compiler_opensrc":145726,
                    "compiler":29772,
                    "flex-2.5.31":217348,
                    "jikespg-1.3":228996,
                    "jpeg-6b":162758,
                    "libmspack":76133,
                    "libpng-1.2.5":120131,
                    "lwip-0.5.3.preproc":116126,
                    "mpeg2dec-0.3.1":64293,
                    "mpgcut-1.1":12248,
                    "replaypc-0.4.0.preproc":80077,
                    "teem-1.6.0-src":1014224,
                    "ttt-0.10.1.preproc":28988,
                    "unrarlib-0.4.0":15566,
                    "zlib-1.1.4":46017
                },
                "sum":2466165
            },
            "clang-trunk-native-Oz":{
                "flags":[
                    "-Oz"
                ],
                "projects":{
                    "OpenTCP-1.0.4":36366,
                    "bzip2-1.0.2":63664,
                    "cg_compiler_opensrc":143898,
                    "compiler":28232,
                    "flex-2.5.31":214266,
                    "jikespg-1.3":224412,
                    "jpeg-6b":155480,
                    "libmspack":75489,
                    "libpng-1.2.5":118909,
                    "lwip-0.5.3.preproc":116126,
                    "mpeg2dec-0.3.1":55005,
                    "mpgcut-1.1":9684,
                    "replaypc-0.4.0.preproc":80077,
                    "teem-1.6.0-src":1012990,
                    "ttt-0.10.1.preproc":28988,
                    "unrarlib-0.4.0":14901,
                    "zlib-1.1.4":46644
                },
                "sum":2425131
            }
        },
        "364270":{
            "clang-trunk-cortex-m0-Os":{
                "flags":[
                    "--target=arm-none-eabi",
                    "-Os",
                    "-mcpu=cortex-m0",
                    "-mthumb",
                    "-isysroot",
                    "/usr/lib/arm-none-eabi",
                    "-iwithsysroot",
                    "/include"
                ],
                "projects":{
                    "OpenTCP-1.0.4":25797,
                    "bzip2-1.0.2":53298,
                    "cg_compiler_opensrc":99038,
                    "compiler":21753,
                    "flex-2.5.31":195199,
                    "jikespg-1.3":176930,
                    "jpeg-6b":115413,
                    "libmspack":55581,
                    "libpng-1.2.5":86043,
                    "lwip-0.5.3.preproc":116126,
                    "mpeg2dec-0.3.1":40370,
                    "mpgcut-1.1":12344,
                    "replaypc-0.4.0.preproc":80077,
                    "teem-1.6.0-src":860813,
                    "ttt-0.10.1.preproc":28988,
                    "unrarlib-0.4.0":11809,
                    "zlib-1.1.4":31338
                },
                "sum":2010917
            },
            "clang-trunk-cortex-m0-Oz":{
                "flags":[
                    "--target=arm-none-eabi",
                    "-Oz",
                    "-mcpu=cortex-m0",
                    "-mthumb",
                    "-isysroot",
                    "/usr/lib/arm-none-eabi",
                    "-iwithsysroot",
                    "/include"
                ],
                "projects":{
                    "OpenTCP-1.0.4":23267,
                    "bzip2-1.0.2":47084,
                    "cg_compiler_opensrc":95692,
                    "compiler":20745,
                    "flex-2.5.31":189401,
                    "jikespg-1.3":168916,
                    "jpeg-6b":108795,
                    "libmspack":53503,
                    "libpng-1.2.5":83695,
                    "lwip-0.5.3.preproc":116126,
                    "mpeg2dec-0.3.1":39170,
                    "mpgcut-1.1":7384,
                    "replaypc-0.4.0.preproc":80077,
                    "teem-1.6.0-src":852393,
                    "ttt-0.10.1.preproc":28988,
                    "unrarlib-0.4.0":11249,
                    "zlib-1.1.4":31096
                },
                "sum":1957581
            },
            "clang-trunk-cortex-m4-Os":{
                "flags":[
                    "--target=arm-none-eabi",
                    "-Os",
                    "-mcpu=cortex-m4",
                    "-mthumb",
                    "-isysroot",
                    "/usr/lib/arm-none-eabi",
                    "-iwithsysroot",
                    "/include"
                ],
                "projects":{
                    "OpenTCP-1.0.4":27427,
                    "bzip2-1.0.2":55478,
                    "cg_compiler_opensrc":103614,
                    "compiler":23167,
                    "flex-2.5.31":211269,
                    "jikespg-1.3":209688,
                    "jpeg-6b":117117,
                    "libmspack":59265,
                    "libpng-1.2.5":90151,
                    "lwip-0.5.3.preproc":116126,
                    "mpeg2dec-0.3.1":42904,
                    "mpgcut-1.1":14500,
                    "replaypc-0.4.0.preproc":80077,
                    "teem-1.6.0-src":953761,
                    "ttt-0.10.1.preproc":28988,
                    "unrarlib-0.4.0":13401,
                    "zlib-1.1.4":32334
                },
                "sum":2179267
            },
            "clang-trunk-cortex-m4-Oz":{
                "flags":[
                    "--target=arm-none-eabi",
                    "-Oz",
                    "-mcpu=cortex-m4",
                    "-mthumb",
                    "-isysroot",
                    "/usr/lib/arm-none-eabi",
                    "-iwithsysroot",
                    "/include"
                ],
                "projects":{
                    "OpenTCP-1.0.4":23377,
                    "bzip2-1.0.2":46828,
                    "cg_compiler_opensrc":95248,
                    "compiler":20813,
                    "flex-2.5.31":191583,
                    "jikespg-1.3":173750,
                    "jpeg-6b":106437,
                    "libmspack":53093,
                    "libpng-1.2.5":84911,
                    "lwip-0.5.3.preproc":116126,
                    "mpeg2dec-0.3.1":40140,
                    "mpgcut-1.1":7844,
                    "replaypc-0.4.0.preproc":80077,
                    "teem-1.6.0-src":910637,
                    "ttt-0.10.1.preproc":28988,
                    "unrarlib-0.4.0":11413,
                    "zlib-1.1.4":29908
                },
                "sum":2021173
            },
            "clang-trunk-native-Os":{
                "flags":[
                    "-Os"
                ],
                "projects":{
                    "OpenTCP-1.0.4":37195,
                    "bzip2-1.0.2":70567,
                    "cg_compiler_opensrc":145726,
                    "compiler":29772,
                    "flex-2.5.31":217348,
                    "jikespg-1.3":228996,
                    "jpeg-6b":162758,
                    "libmspack":76133,
                    "libpng-1.2.5":120131,
                    "lwip-0.5.3.preproc":116126,
                    "mpeg2dec-0.3.1":64293,
                    "mpgcut-1.1":12248,
                    "replaypc-0.4.0.preproc":80077,
                    "teem-1.6.0-src":1014224,
                    "ttt-0.10.1.preproc":28988,
                    "unrarlib-0.4.0":15566,
                    "zlib-1.1.4":46017
                },
                "sum":2466165
            },
            "clang-trunk-native-Oz":{
                "flags":[
                    "-Oz"
                ],
                "projects":{
                    "OpenTCP-1.0.4":36366,
                    "bzip2-1.0.2":63664,
                    "cg_compiler_opensrc":143898,
                    "compiler":28232,
                    "flex-2.5.31":214266,
                    "jikespg-1.3":224412,
                    "jpeg-6b":155480,
                    "libmspack":75489,
                    "libpng-1.2.5":118909,
                    "lwip-0.5.3.preproc":116126,
                    "mpeg2dec-0.3.1":55005,
                    "mpgcut-1.1":9684,
                    "replaypc-0.4.0.preproc":80077,
                    "teem-1.6.0-src":1012990,
                    "ttt-0.10.1.preproc":28988,
                    "unrarlib-0.4.0":14901,
                    "zlib-1.1.4":46644
                },
                "sum":2425131
            }
        },
        "364271":{
            "clang-trunk-cortex-m0-Os":{
                "flags":[
                    "--target=arm-none-eabi",
                    "-Os",
                    "-mcpu=cortex-m0",
                    "-mthumb",
                    "-isysroot",
                    "/usr/lib/arm-none-eabi",
                    "-iwithsysroot",
                    "/include"
                ],
                "projects":{
                    "OpenTCP-1.0.4":25797,
                    "bzip2-1.0.2":53298,
                    "cg_compiler_opensrc":99038,
                    "compiler":21753,
                    "flex-2.5.31":195199,
                    "jikespg-1.3":176930,
                    "jpeg-6b":115413,
                    "libmspack":55581,
                    "libpng-1.2.5":86043,
                    "lwip-0.5.3.preproc":116126,
                    "mpeg2dec-0.3.1":40370,
                    "mpgcut-1.1":12344,
                    "replaypc-0.4.0.preproc":80077,
                    "teem-1.6.0-src":860813,
                    "ttt-0.10.1.preproc":28988,
                    "unrarlib-0.4.0":11809,
                    "zlib-1.1.4":31338
                },
                "sum":2010917
            },
            "clang-trunk-cortex-m0-Oz":{
                "flags":[
                    "--target=arm-none-eabi",
                    "-Oz",
                    "-mcpu=cortex-m0",
                    "-mthumb",
                    "-isysroot",
                    "/usr/lib/arm-none-eabi",
                    "-iwithsysroot",
                    "/include"
                ],
                "projects":{
                    "OpenTCP-1.0.4":23267,
                    "bzip2-1.0.2":47084,
                    "cg_compiler_opensrc":95692,
                    "compiler":20745,
                    "flex-2.5.31":189401,
                    "jikespg-1.3":168916,
                    "jpeg-6b":108795,
                    "libmspack":53503,
                    "libpng-1.2.5":83695,
                    "lwip-0.5.3.preproc":116126,
                    "mpeg2dec-0.3.1":39170,
                    "mpgcut-1.1":7384,
                    "replaypc-0.4.0.preproc":80077,
                    "teem-1.6.0-src":852393,
                    "ttt-0.10.1.preproc":28988,
                    "unrarlib-0.4.0":11249,
                    "zlib-1.1.4":31096
                },
                "sum":1957581
            },
            "clang-trunk-cortex-m4-Os":{
                "flags":[
                    "--target=arm-none-eabi",
                    "-Os",
                    "-mcpu=cortex-m4",
                    "-mthumb",
                    "-isysroot",
                    "/usr/lib/arm-none-eabi",
                    "-iwithsysroot",
                    "/include"
                ],
                "projects":{
                    "OpenTCP-1.0.4":27427,
                    "bzip2-1.0.2":55478,
                    "cg_compiler_opensrc":103614,
                    "compiler":23167,
                    "flex-2.5.31":211269,
                    "jikespg-1.3":209688,
                    "jpeg-6b":117117,
                    "libmspack":59265,
                    "libpng-1.2.5":90151,
                    "lwip-0.5.3.preproc":116126,
                    "mpeg2dec-0.3.1":42904,
                    "mpgcut-1.1":14500,
                    "replaypc-0.4.0.preproc":80077,
                    "teem-1.6.0-src":953761,
                    "ttt-0.10.1.preproc":28988,
                    "unrarlib-0.4.0":13401,
                    "zlib-1.1.4":32334
                },
                "sum":2179267
            },
            "clang-trunk-cortex-m4-Oz":{
                "flags":[
                    "--target=arm-none-eabi",
                    "-Oz",
                    "-mcpu=cortex-m4",
                    "-mthumb",
                    "-isysroot",
                    "/usr/lib/arm-none-eabi",
                    "-iwithsysroot",
                    "/include"
                ],
                "projects":{
                    "OpenTCP-1.0.4":23377,
                    "bzip2-1.0.2":46828,
                    "cg_compiler_opensrc":95248,
                    "compiler":20813,
                    "flex-2.5.31":191583,
                    "jikespg-1.3":173750,
                    "jpeg-6b":106437,
                    "libmspack":53093,
                    "libpng-1.2.5":84911,
                    "lwip-0.5.3.preproc":116126,
                    "mpeg2dec-0.3.1":40140,
                    "mpgcut-1.1":7844,
                    "replaypc-0.4.0.preproc":80077,
                    "teem-1.6.0-src":910637,
                    "ttt-0.10.1.preproc":28988,
                    "unrarlib-0.4.0":11413,
                    "zlib-1.1.4":29908
                },
                "sum":2021173
            },
            "clang-trunk-native-Os":{
                "flags":[
                    "-Os"
                ],
                "projects":{
                    "OpenTCP-1.0.4":37195,
                    "bzip2-1.0.2":70567,
                    "cg_compiler_opensrc":145726,
                    "compiler":29772,
                    "flex-2.5.31":217348,
                    "jikespg-1.3":228996,
                    "jpeg-6b":162758,
                    "libmspack":76133,
                    "libpng-1.2.5":120131,
                    "lwip-0.5.3.preproc":116126,
                    "mpeg2dec-0.3.1":64293,
                    "mpgcut-1.1":12248,
                    "replaypc-0.4.0.preproc":80077,
                    "teem-1.6.0-src":1014224,
                    "ttt-0.10.1.preproc":28988,
                    "unrarlib-0.4.0":15566,
                    "zlib-1.1.4":46017
                },
                "sum":2466165
            },
            "clang-trunk-native-Oz":{
                "flags":[
                    "-Oz"
                ],
                "projects":{
                    "OpenTCP-1.0.4":36366,
                    "bzip2-1.0.2":63664,
                    "cg_compiler_opensrc":143898,
                    "compiler":28232,
                    "flex-2.5.31":214266,
                    "jikespg-1.3":224412,
                    "jpeg-6b":155480,
                    "libmspack":75489,
                    "libpng-1.2.5":118909,
                    "lwip-0.5.3.preproc":116126,
                    "mpeg2dec-0.3.1":55005,
                    "mpgcut-1.1":9684,
                    "replaypc-0.4.0.preproc":80077,
                    "teem-1.6.0-src":1012990,
                    "ttt-0.10.1.preproc":28988,
                    "unrarlib-0.4.0":14901,
                    "zlib-1.1.4":46644
                },
                "sum":2425131
            }
        }
    }
}