{
    "date":"2018-02-10",
    "revisions":{
        "324784":{
            "clang-trunk-cortex-m0-Os":{
                "flags":[
                    "--target=arm-none-eabi",
                    "-Os",
                    "-mcpu=cortex-m0",
                    "-mthumb",
                    "-isysroot",
                    "/usr/lib/arm-none-eabi",
                    "-iwithsysroot",
                    "/include"
                ],
                "projects":{
                    "OpenTCP-1.0.4":26173,
                    "bzip2-1.0.2":56984,
                    "cg_compiler_opensrc":100286,
                    "compiler":22020,
                    "flex-2.5.31":197553,
                    "jikespg-1.3":179490,
                    "jpeg-6b":119949,
                    "libmspack":57976,
                    "libpng-1.2.5":90889,
                    "lwip-0.5.3.preproc":116126,
                    "mpeg2dec-0.3.1":43564,
                    "mpgcut-1.1":12650,
                    "replaypc-0.4.0.preproc":80077,
                    "teem-1.6.0-src":875773,
                    "ttt-0.10.1.preproc":28988,
                    "unrarlib-0.4.0":11954,
                    "zlib-1.1.4":32086
                },
                "sum":2052538
            },
            "clang-trunk-cortex-m0-Oz":{
                "flags":[
                    "--target=arm-none-eabi",
                    "-Oz",
                    "-mcpu=cortex-m0",
                    "-mthumb",
                    "-isysroot",
                    "/usr/lib/arm-none-eabi",
                    "-iwithsysroot",
                    "/include"
                ],
                "projects":{
                    "OpenTCP-1.0.4":23931,
                    "bzip2-1.0.2":49104,
                    "cg_compiler_opensrc":97036,
                    "compiler":21188,
                    "flex-2.5.31":192173,
                    "jikespg-1.3":171386,
                    "jpeg-6b":112147,
                    "libmspack":56208,
                    "libpng-1.2.5":88215,
                    "lwip-0.5.3.preproc":116126,
                    "mpeg2dec-0.3.1":41790,
                    "mpgcut-1.1":7622,
                    "replaypc-0.4.0.preproc":80077,
                    "teem-1.6.0-src":867809,
                    "ttt-0.10.1.preproc":28988,
                    "unrarlib-0.4.0":11382,
                    "zlib-1.1.4":31860
                },
                "sum":1997042
            },
            "clang-trunk-cortex-m4-Os":{
                "flags":[
                    "--target=arm-none-eabi",
                    "-Os",
                    "-mcpu=cortex-m4",
                    "-mthumb",
                    "-isysroot",
                    "/usr/lib/arm-none-eabi",
                    "-iwithsysroot",
                    "/include"
                ],
                "projects":{
                    "OpenTCP-1.0.4":26901,
                    "bzip2-1.0.2":61830,
                    "cg_compiler_opensrc":103960,
                    "compiler":23142,
                    "flex-2.5.31":211549,
                    "jikespg-1.3":207536,
                    "jpeg-6b":118095,
                    "libmspack":60630,
                    "libpng-1.2.5":90705,
                    "lwip-0.5.3.preproc":116126,
                    "mpeg2dec-0.3.1":43706,
                    "mpgcut-1.1":14782,
                    "replaypc-0.4.0.preproc":80077,
                    "teem-1.6.0-src":950907,
                    "ttt-0.10.1.preproc":28988,
                    "unrarlib-0.4.0":13484,
                    "zlib-1.1.4":32190
                },
                "sum":2184608
            },
            "clang-trunk-cortex-m4-Oz":{
                "flags":[
                    "--target=arm-none-eabi",
                    "-Oz",
                    "-mcpu=cortex-m4",
                    "-mthumb",
                    "-isysroot",
                    "/usr/lib/arm-none-eabi",
                    "-iwithsysroot",
                    "/include"
                ],
                "projects":{
                    "OpenTCP-1.0.4":24019,
                    "bzip2-1.0.2":49608,
                    "cg_compiler_opensrc":95906,
                    "compiler":20804,
                    "flex-2.5.31":192413,
                    "jikespg-1.3":174414,
                    "jpeg-6b":107863,
                    "libmspack":55482,
                    "libpng-1.2.5":86047,
                    "lwip-0.5.3.preproc":116126,
                    "mpeg2dec-0.3.1":40424,
                    "mpgcut-1.1":8022,
                    "replaypc-0.4.0.preproc":80077,
                    "teem-1.6.0-src":918273,
                    "ttt-0.10.1.preproc":28988,
                    "unrarlib-0.4.0":11650,
                    "zlib-1.1.4":31228
                },
                "sum":2041344
            },
            "clang-trunk-native-Os":{
                "flags":[
                    "-Os"
                ],
                "projects":{
                    "OpenTCP-1.0.4":37239,
                    "bzip2-1.0.2":74609,
                    "cg_compiler_opensrc":141845,
                    "compiler":29403,
                    "flex-2.5.31":215317,
                    "jikespg-1.3":228729,
                    "jpeg-6b":160389,
                    "libmspack":76509,
                    "libpng-1.2.5":117681,
                    "lwip-0.5.3.preproc":116126,
                    "mpeg2dec-0.3.1":64806,
                    "mpgcut-1.1":12143,
                    "replaypc-0.4.0.preproc":80077,
                    "teem-1.6.0-src":1006396,
                    "ttt-0.10.1.preproc":28988,
                    "unrarlib-0.4.0":15259,
                    "zlib-1.1.4":45058
                },
                "sum":2450574
            },
            "clang-trunk-native-Oz":{
                "flags":[
                    "-Oz"
                ],
                "projects":{
                    "OpenTCP-1.0.4":35052,
                    "bzip2-1.0.2":64569,
                    "cg_compiler_opensrc":140369,
                    "compiler":28023,
                    "flex-2.5.31":212490,
                    "jikespg-1.3":224294,
                    "jpeg-6b":151966,
                    "libmspack":77008,
                    "libpng-1.2.5":115071,
                    "lwip-0.5.3.preproc":116126,
                    "mpeg2dec-0.3.1":53909,
                    "mpgcut-1.1":9669,
                    "replaypc-0.4.0.preproc":80077,
                    "teem-1.6.0-src":1006817,
                    "ttt-0.10.1.preproc":28988,
                    "unrarlib-0.4.0":14830,
                    "zlib-1.1.4":46032
                },
                "sum":2405290
            }
        },
        "324785":{
            "clang-trunk-cortex-m0-Os":{
                "flags":[
                    "--target=arm-none-eabi",
                    "-Os",
                    "-mcpu=cortex-m0",
                    "-mthumb",
                    "-isysroot",
                    "/usr/lib/arm-none-eabi",
                    "-iwithsysroot",
                    "/include"
                ],
                "projects":{
                    "OpenTCP-1.0.4":26173,
                    "bzip2-1.0.2":56984,
                    "cg_compiler_opensrc":100286,
                    "compiler":22020,
                    "flex-2.5.31":197553,
                    "jikespg-1.3":179490,
                    "jpeg-6b":119949,
                    "libmspack":57976,
                    "libpng-1.2.5":90889,
                    "lwip-0.5.3.preproc":116126,
                    "mpeg2dec-0.3.1":43564,
                    "mpgcut-1.1":12650,
                    "replaypc-0.4.0.preproc":80077,
                    "teem-1.6.0-src":875773,
                    "ttt-0.10.1.preproc":28988,
                    "unrarlib-0.4.0":11954,
                    "zlib-1.1.4":32086
                },
                "sum":2052538
            },
            "clang-trunk-cortex-m0-Oz":{
                "flags":[
                    "--target=arm-none-eabi",
                    "-Oz",
                    "-mcpu=cortex-m0",
                    "-mthumb",
                    "-isysroot",
                    "/usr/lib/arm-none-eabi",
                    "-iwithsysroot",
                    "/include"
                ],
                "projects":{
                    "OpenTCP-1.0.4":23931,
                    "bzip2-1.0.2":49104,
                    "cg_compiler_opensrc":97036,
                    "compiler":21188,
                    "flex-2.5.31":192173,
                    "jikespg-1.3":171386,
                    "jpeg-6b":112147,
                    "libmspack":56208,
                    "libpng-1.2.5":88215,
                    "lwip-0.5.3.preproc":116126,
                    "mpeg2dec-0.3.1":41790,
                    "mpgcut-1.1":7622,
                    "replaypc-0.4.0.preproc":80077,
                    "teem-1.6.0-src":867809,
                    "ttt-0.10.1.preproc":28988,
                    "unrarlib-0.4.0":11382,
                    "zlib-1.1.4":31860
                },
                "sum":1997042
            },
            "clang-trunk-cortex-m4-Os":{
                "flags":[
                    "--target=arm-none-eabi",
                    "-Os",
                    "-mcpu=cortex-m4",
                    "-mthumb",
                    "-isysroot",
                    "/usr/lib/arm-none-eabi",
                    "-iwithsysroot",
                    "/include"
                ],
                "projects":{
                    "OpenTCP-1.0.4":26901,
                    "bzip2-1.0.2":61830,
                    "cg_compiler_opensrc":103960,
                    "compiler":23142,
                    "flex-2.5.31":211549,
                    "jikespg-1.3":207536,
                    "jpeg-6b":118095,
                    "libmspack":60630,
                    "libpng-1.2.5":90705,
                    "lwip-0.5.3.preproc":116126,
                    "mpeg2dec-0.3.1":43706,
                    "mpgcut-1.1":14782,
                    "replaypc-0.4.0.preproc":80077,
                    "teem-1.6.0-src":950907,
                    "ttt-0.10.1.preproc":28988,
                    "unrarlib-0.4.0":13484,
                    "zlib-1.1.4":32190
                },
                "sum":2184608
            },
            "clang-trunk-cortex-m4-Oz":{
                "flags":[
                    "--target=arm-none-eabi",
                    "-Oz",
                    "-mcpu=cortex-m4",
                    "-mthumb",
                    "-isysroot",
                    "/usr/lib/arm-none-eabi",
                    "-iwithsysroot",
                    "/include"
                ],
                "projects":{
                    "OpenTCP-1.0.4":24019,
                    "bzip2-1.0.2":49608,
                    "cg_compiler_opensrc":95906,
                    "compiler":20804,
                    "flex-2.5.31":192413,
                    "jikespg-1.3":174414,
                    "jpeg-6b":107863,
                    "libmspack":55482,
                    "libpng-1.2.5":86047,
                    "lwip-0.5.3.preproc":116126,
                    "mpeg2dec-0.3.1":40424,
                    "mpgcut-1.1":8022,
                    "replaypc-0.4.0.preproc":80077,
                    "teem-1.6.0-src":918273,
                    "ttt-0.10.1.preproc":28988,
                    "unrarlib-0.4.0":11650,
                    "zlib-1.1.4":31228
                },
                "sum":2041344
            },
            "clang-trunk-native-Os":{
                "flags":[
                    "-Os"
                ],
                "projects":{
                    "OpenTCP-1.0.4":37239,
                    "bzip2-1.0.2":74609,
                    "cg_compiler_opensrc":141845,
                    "compiler":29403,
                    "flex-2.5.31":215317,
                    "jikespg-1.3":228729,
                    "jpeg-6b":160389,
                    "libmspack":76509,
                    "libpng-1.2.5":117681,
                    "lwip-0.5.3.preproc":116126,
                    "mpeg2dec-0.3.1":64806,
                    "mpgcut-1.1":12143,
                    "replaypc-0.4.0.preproc":80077,
                    "teem-1.6.0-src":1006396,
                    "ttt-0.10.1.preproc":28988,
                    "unrarlib-0.4.0":15259,
                    "zlib-1.1.4":45058
                },
                "sum":2450574
            },
            "clang-trunk-native-Oz":{
                "flags":[
                    "-Oz"
                ],
                "projects":{
                    "OpenTCP-1.0.4":35052,
                    "bzip2-1.0.2":64569,
                    "cg_compiler_opensrc":140369,
                    "compiler":28023,
                    "flex-2.5.31":212490,
                    "jikespg-1.3":224294,
                    "jpeg-6b":151966,
                    "libmspack":77008,
                    "libpng-1.2.5":115071,
                    "lwip-0.5.3.preproc":116126,
                    "mpeg2dec-0.3.1":53909,
                    "mpgcut-1.1":9669,
                    "replaypc-0.4.0.preproc":80077,
                    "teem-1.6.0-src":1006817,
                    "ttt-0.10.1.preproc":28988,
                    "unrarlib-0.4.0":14830,
                    "zlib-1.1.4":46032
                },
                "sum":2405290
            }
        },
        "324787":{
            "clang-trunk-cortex-m0-Os":{
                "flags":[
                    "--target=arm-none-eabi",
                    "-Os",
                    "-mcpu=cortex-m0",
                    "-mthumb",
                    "-isysroot",
                    "/usr/lib/arm-none-eabi",
                    "-iwithsysroot",
                    "/include"
                ],
                "projects":{
                    "OpenTCP-1.0.4":26173,
                    "bzip2-1.0.2":56984,
                    "cg_compiler_opensrc":100286,
                    "compiler":22020,
                    "flex-2.5.31":197553,
                    "jikespg-1.3":179490,
                    "jpeg-6b":119949,
                    "libmspack":57976,
                    "libpng-1.2.5":90889,
                    "lwip-0.5.3.preproc":116126,
                    "mpeg2dec-0.3.1":43564,
                    "mpgcut-1.1":12650,
                    "replaypc-0.4.0.preproc":80077,
                    "teem-1.6.0-src":875773,
                    "ttt-0.10.1.preproc":28988,
                    "unrarlib-0.4.0":11954,
                    "zlib-1.1.4":32086
                },
                "sum":2052538
            },
            "clang-trunk-cortex-m0-Oz":{
                "flags":[
                    "--target=arm-none-eabi",
                    "-Oz",
                    "-mcpu=cortex-m0",
                    "-mthumb",
                    "-isysroot",
                    "/usr/lib/arm-none-eabi",
                    "-iwithsysroot",
                    "/include"
                ],
                "projects":{
                    "OpenTCP-1.0.4":23931,
                    "bzip2-1.0.2":49104,
                    "cg_compiler_opensrc":97036,
                    "compiler":21188,
                    "flex-2.5.31":192173,
                    "jikespg-1.3":171386,
                    "jpeg-6b":112147,
                    "libmspack":56208,
                    "libpng-1.2.5":88215,
                    "lwip-0.5.3.preproc":116126,
                    "mpeg2dec-0.3.1":41790,
                    "mpgcut-1.1":7622,
                    "replaypc-0.4.0.preproc":80077,
                    "teem-1.6.0-src":867809,
                    "ttt-0.10.1.preproc":28988,
                    "unrarlib-0.4.0":11382,
                    "zlib-1.1.4":31860
                },
                "sum":1997042
            },
            "clang-trunk-cortex-m4-Os":{
                "flags":[
                    "--target=arm-none-eabi",
                    "-Os",
                    "-mcpu=cortex-m4",
                    "-mthumb",
                    "-isysroot",
                    "/usr/lib/arm-none-eabi",
                    "-iwithsysroot",
                    "/include"
                ],
                "projects":{
                    "OpenTCP-1.0.4":26901,
                    "bzip2-1.0.2":61830,
                    "cg_compiler_opensrc":103960,
                    "compiler":23142,
                    "flex-2.5.31":211549,
                    "jikespg-1.3":207536,
                    "jpeg-6b":118095,
                    "libmspack":60630,
                    "libpng-1.2.5":90705,
                    "lwip-0.5.3.preproc":116126,
                    "mpeg2dec-0.3.1":43706,
                    "mpgcut-1.1":14782,
                    "replaypc-0.4.0.preproc":80077,
                    "teem-1.6.0-src":950907,
                    "ttt-0.10.1.preproc":28988,
                    "unrarlib-0.4.0":13484,
                    "zlib-1.1.4":32190
                },
                "sum":2184608
            },
            "clang-trunk-cortex-m4-Oz":{
                "flags":[
                    "--target=arm-none-eabi",
                    "-Oz",
                    "-mcpu=cortex-m4",
                    "-mthumb",
                    "-isysroot",
                    "/usr/lib/arm-none-eabi",
                    "-iwithsysroot",
                    "/include"
                ],
                "projects":{
                    "OpenTCP-1.0.4":24019,
                    "bzip2-1.0.2":49608,
                    "cg_compiler_opensrc":95906,
                    "compiler":20804,
                    "flex-2.5.31":192413,
                    "jikespg-1.3":174414,
                    "jpeg-6b":107863,
                    "libmspack":55482,
                    "libpng-1.2.5":86047,
                    "lwip-0.5.3.preproc":116126,
                    "mpeg2dec-0.3.1":40424,
                    "mpgcut-1.1":8022,
                    "replaypc-0.4.0.preproc":80077,
                    "teem-1.6.0-src":918273,
                    "ttt-0.10.1.preproc":28988,
                    "unrarlib-0.4.0":11650,
                    "zlib-1.1.4":31228
                },
                "sum":2041344
            },
            "clang-trunk-native-Os":{
                "flags":[
                    "-Os"
                ],
                "projects":{
                    "OpenTCP-1.0.4":37239,
                    "bzip2-1.0.2":74609,
                    "cg_compiler_opensrc":141845,
                    "compiler":29403,
                    "flex-2.5.31":215317,
                    "jikespg-1.3":228729,
                    "jpeg-6b":160389,
                    "libmspack":76509,
                    "libpng-1.2.5":117681,
                    "lwip-0.5.3.preproc":116126,
                    "mpeg2dec-0.3.1":64806,
                    "mpgcut-1.1":12143,
                    "replaypc-0.4.0.preproc":80077,
                    "teem-1.6.0-src":1006396,
                    "ttt-0.10.1.preproc":28988,
                    "unrarlib-0.4.0":15259,
                    "zlib-1.1.4":45058
                },
                "sum":2450574
            },
            "clang-trunk-native-Oz":{
                "flags":[
                    "-Oz"
                ],
                "projects":{
                    "OpenTCP-1.0.4":35052,
                    "bzip2-1.0.2":64569,
                    "cg_compiler_opensrc":140369,
                    "compiler":28023,
                    "flex-2.5.31":212490,
                    "jikespg-1.3":224294,
                    "jpeg-6b":151966,
                    "libmspack":77008,
                    "libpng-1.2.5":115071,
                    "lwip-0.5.3.preproc":116126,
                    "mpeg2dec-0.3.1":53909,
                    "mpgcut-1.1":9669,
                    "replaypc-0.4.0.preproc":80077,
                    "teem-1.6.0-src":1006817,
                    "ttt-0.10.1.preproc":28988,
                    "unrarlib-0.4.0":14830,
                    "zlib-1.1.4":46032
                },
                "sum":2405290
            }
        },
        "324788":{
            "clang-trunk-cortex-m0-Os":{
                "flags":[
                    "--target=arm-none-eabi",
                    "-Os",
                    "-mcpu=cortex-m0",
                    "-mthumb",
                    "-isysroot",
                    "/usr/lib/arm-none-eabi",
                    "-iwithsysroot",
                    "/include"
                ],
                "projects":{
                    "OpenTCP-1.0.4":26173,
                    "bzip2-1.0.2":56984,
                    "cg_compiler_opensrc":100286,
                    "compiler":22020,
                    "flex-2.5.31":197553,
                    "jikespg-1.3":179490,
                    "jpeg-6b":119949,
                    "libmspack":57976,
                    "libpng-1.2.5":90889,
                    "lwip-0.5.3.preproc":116126,
                    "mpeg2dec-0.3.1":43564,
                    "mpgcut-1.1":12650,
                    "replaypc-0.4.0.preproc":80077,
                    "teem-1.6.0-src":875773,
                    "ttt-0.10.1.preproc":28988,
                    "unrarlib-0.4.0":11954,
                    "zlib-1.1.4":32086
                },
                "sum":2052538
            },
            "clang-trunk-cortex-m0-Oz":{
                "flags":[
                    "--target=arm-none-eabi",
                    "-Oz",
                    "-mcpu=cortex-m0",
                    "-mthumb",
                    "-isysroot",
                    "/usr/lib/arm-none-eabi",
                    "-iwithsysroot",
                    "/include"
                ],
                "projects":{
                    "OpenTCP-1.0.4":23931,
                    "bzip2-1.0.2":49104,
                    "cg_compiler_opensrc":97036,
                    "compiler":21188,
                    "flex-2.5.31":192173,
                    "jikespg-1.3":171386,
                    "jpeg-6b":112147,
                    "libmspack":56208,
                    "libpng-1.2.5":88215,
                    "lwip-0.5.3.preproc":116126,
                    "mpeg2dec-0.3.1":41790,
                    "mpgcut-1.1":7622,
                    "replaypc-0.4.0.preproc":80077,
                    "teem-1.6.0-src":867809,
                    "ttt-0.10.1.preproc":28988,
                    "unrarlib-0.4.0":11382,
                    "zlib-1.1.4":31860
                },
                "sum":1997042
            },
            "clang-trunk-cortex-m4-Os":{
                "flags":[
                    "--target=arm-none-eabi",
                    "-Os",
                    "-mcpu=cortex-m4",
                    "-mthumb",
                    "-isysroot",
                    "/usr/lib/arm-none-eabi",
                    "-iwithsysroot",
                    "/include"
                ],
                "projects":{
                    "OpenTCP-1.0.4":26901,
                    "bzip2-1.0.2":61830,
                    "cg_compiler_opensrc":103960,
                    "compiler":23142,
                    "flex-2.5.31":211549,
                    "jikespg-1.3":207536,
                    "jpeg-6b":118095,
                    "libmspack":60630,
                    "libpng-1.2.5":90705,
                    "lwip-0.5.3.preproc":116126,
                    "mpeg2dec-0.3.1":43706,
                    "mpgcut-1.1":14782,
                    "replaypc-0.4.0.preproc":80077,
                    "teem-1.6.0-src":950907,
                    "ttt-0.10.1.preproc":28988,
                    "unrarlib-0.4.0":13484,
                    "zlib-1.1.4":32190
                },
                "sum":2184608
            },
            "clang-trunk-cortex-m4-Oz":{
                "flags":[
                    "--target=arm-none-eabi",
                    "-Oz",
                    "-mcpu=cortex-m4",
                    "-mthumb",
                    "-isysroot",
                    "/usr/lib/arm-none-eabi",
                    "-iwithsysroot",
                    "/include"
                ],
                "projects":{
                    "OpenTCP-1.0.4":24019,
                    "bzip2-1.0.2":49608,
                    "cg_compiler_opensrc":95906,
                    "compiler":20804,
                    "flex-2.5.31":192413,
                    "jikespg-1.3":174414,
                    "jpeg-6b":107863,
                    "libmspack":55482,
                    "libpng-1.2.5":86047,
                    "lwip-0.5.3.preproc":116126,
                    "mpeg2dec-0.3.1":40424,
                    "mpgcut-1.1":8022,
                    "replaypc-0.4.0.preproc":80077,
                    "teem-1.6.0-src":918273,
                    "ttt-0.10.1.preproc":28988,
                    "unrarlib-0.4.0":11650,
                    "zlib-1.1.4":31228
                },
                "sum":2041344
            },
            "clang-trunk-native-Os":{
                "flags":[
                    "-Os"
                ],
                "projects":{
                    "OpenTCP-1.0.4":37239,
                    "bzip2-1.0.2":74609,
                    "cg_compiler_opensrc":141845,
                    "compiler":29403,
                    "flex-2.5.31":215317,
                    "jikespg-1.3":228729,
                    "jpeg-6b":160389,
                    "libmspack":76509,
                    "libpng-1.2.5":117681,
                    "lwip-0.5.3.preproc":116126,
                    "mpeg2dec-0.3.1":64806,
                    "mpgcut-1.1":12143,
                    "replaypc-0.4.0.preproc":80077,
                    "teem-1.6.0-src":1006396,
                    "ttt-0.10.1.preproc":28988,
                    "unrarlib-0.4.0":15259,
                    "zlib-1.1.4":45058
                },
                "sum":2450574
            },
            "clang-trunk-native-Oz":{
                "flags":[
                    "-Oz"
                ],
                "projects":{
                    "OpenTCP-1.0.4":35052,
                    "bzip2-1.0.2":64569,
                    "cg_compiler_opensrc":140369,
                    "compiler":28023,
                    "flex-2.5.31":212490,
                    "jikespg-1.3":224294,
                    "jpeg-6b":151966,
                    "libmspack":77008,
                    "libpng-1.2.5":115071,
                    "lwip-0.5.3.preproc":116126,
                    "mpeg2dec-0.3.1":53909,
                    "mpgcut-1.1":9669,
                    "replaypc-0.4.0.preproc":80077,
                    "teem-1.6.0-src":1006817,
                    "ttt-0.10.1.preproc":28988,
                    "unrarlib-0.4.0":14830,
                    "zlib-1.1.4":46032
                },
                "sum":2405290
            }
        },
        "324790":{
            "clang-trunk-cortex-m0-Os":{
                "flags":[
                    "--target=arm-none-eabi",
                    "-Os",
                    "-mcpu=cortex-m0",
                    "-mthumb",
                    "-isysroot",
                    "/usr/lib/arm-none-eabi",
                    "-iwithsysroot",
                    "/include"
                ],
                "projects":{
                    "OpenTCP-1.0.4":26173,
                    "bzip2-1.0.2":56984,
                    "cg_compiler_opensrc":100286,
                    "compiler":22020,
                    "flex-2.5.31":197553,
                    "jikespg-1.3":179490,
                    "jpeg-6b":119949,
                    "libmspack":57976,
                    "libpng-1.2.5":90889,
                    "lwip-0.5.3.preproc":116126,
                    "mpeg2dec-0.3.1":43564,
                    "mpgcut-1.1":12650,
                    "replaypc-0.4.0.preproc":80077,
                    "teem-1.6.0-src":875773,
                    "ttt-0.10.1.preproc":28988,
                    "unrarlib-0.4.0":11954,
                    "zlib-1.1.4":32086
                },
                "sum":2052538
            },
            "clang-trunk-cortex-m0-Oz":{
                "flags":[
                    "--target=arm-none-eabi",
                    "-Oz",
                    "-mcpu=cortex-m0",
                    "-mthumb",
                    "-isysroot",
                    "/usr/lib/arm-none-eabi",
                    "-iwithsysroot",
                    "/include"
                ],
                "projects":{
                    "OpenTCP-1.0.4":23931,
                    "bzip2-1.0.2":49104,
                    "cg_compiler_opensrc":97036,
                    "compiler":21188,
                    "flex-2.5.31":192173,
                    "jikespg-1.3":171386,
                    "jpeg-6b":112147,
                    "libmspack":56208,
                    "libpng-1.2.5":88215,
                    "lwip-0.5.3.preproc":116126,
                    "mpeg2dec-0.3.1":41790,
                    "mpgcut-1.1":7622,
                    "replaypc-0.4.0.preproc":80077,
                    "teem-1.6.0-src":867809,
                    "ttt-0.10.1.preproc":28988,
                    "unrarlib-0.4.0":11382,
                    "zlib-1.1.4":31860
                },
                "sum":1997042
            },
            "clang-trunk-cortex-m4-Os":{
                "flags":[
                    "--target=arm-none-eabi",
                    "-Os",
                    "-mcpu=cortex-m4",
                    "-mthumb",
                    "-isysroot",
                    "/usr/lib/arm-none-eabi",
                    "-iwithsysroot",
                    "/include"
                ],
                "projects":{
                    "OpenTCP-1.0.4":26901,
                    "bzip2-1.0.2":61830,
                    "cg_compiler_opensrc":103960,
                    "compiler":23142,
                    "flex-2.5.31":211549,
                    "jikespg-1.3":207536,
                    "jpeg-6b":118095,
                    "libmspack":60630,
                    "libpng-1.2.5":90705,
                    "lwip-0.5.3.preproc":116126,
                    "mpeg2dec-0.3.1":43706,
                    "mpgcut-1.1":14782,
                    "replaypc-0.4.0.preproc":80077,
                    "teem-1.6.0-src":950907,
                    "ttt-0.10.1.preproc":28988,
                    "unrarlib-0.4.0":13484,
                    "zlib-1.1.4":32190
                },
                "sum":2184608
            },
            "clang-trunk-cortex-m4-Oz":{
                "flags":[
                    "--target=arm-none-eabi",
                    "-Oz",
                    "-mcpu=cortex-m4",
                    "-mthumb",
                    "-isysroot",
                    "/usr/lib/arm-none-eabi",
                    "-iwithsysroot",
                    "/include"
                ],
                "projects":{
                    "OpenTCP-1.0.4":24019,
                    "bzip2-1.0.2":49608,
                    "cg_compiler_opensrc":95906,
                    "compiler":20804,
                    "flex-2.5.31":192413,
                    "jikespg-1.3":174414,
                    "jpeg-6b":107863,
                    "libmspack":55482,
                    "libpng-1.2.5":86047,
                    "lwip-0.5.3.preproc":116126,
                    "mpeg2dec-0.3.1":40424,
                    "mpgcut-1.1":8022,
                    "replaypc-0.4.0.preproc":80077,
                    "teem-1.6.0-src":918273,
                    "ttt-0.10.1.preproc":28988,
                    "unrarlib-0.4.0":11650,
                    "zlib-1.1.4":31228
                },
                "sum":2041344
            },
            "clang-trunk-native-Os":{
                "flags":[
                    "-Os"
                ],
                "projects":{
                    "OpenTCP-1.0.4":37239,
                    "bzip2-1.0.2":74609,
                    "cg_compiler_opensrc":141845,
                    "compiler":29403,
                    "flex-2.5.31":215317,
                    "jikespg-1.3":228729,
                    "jpeg-6b":160389,
                    "libmspack":76509,
                    "libpng-1.2.5":117681,
                    "lwip-0.5.3.preproc":116126,
                    "mpeg2dec-0.3.1":64806,
                    "mpgcut-1.1":12143,
                    "replaypc-0.4.0.preproc":80077,
                    "teem-1.6.0-src":1006396,
                    "ttt-0.10.1.preproc":28988,
                    "unrarlib-0.4.0":15259,
                    "zlib-1.1.4":45058
                },
                "sum":2450574
            },
            "clang-trunk-native-Oz":{
                "flags":[
                    "-Oz"
                ],
                "projects":{
                    "OpenTCP-1.0.4":35052,
                    "bzip2-1.0.2":64569,
                    "cg_compiler_opensrc":140369,
                    "compiler":28023,
                    "flex-2.5.31":212490,
                    "jikespg-1.3":224294,
                    "jpeg-6b":151966,
                    "libmspack":77008,
                    "libpng-1.2.5":115071,
                    "lwip-0.5.3.preproc":116126,
                    "mpeg2dec-0.3.1":53909,
                    "mpgcut-1.1":9669,
                    "replaypc-0.4.0.preproc":80077,
                    "teem-1.6.0-src":1006817,
                    "ttt-0.10.1.preproc":28988,
                    "unrarlib-0.4.0":14830,
                    "zlib-1.1.4":46032
                },
                "sum":2405290
            }
        },
        "324791":{
            "clang-trunk-cortex-m0-Os":{
                "flags":[
                    "--target=arm-none-eabi",
                    "-Os",
                    "-mcpu=cortex-m0",
                    "-mthumb",
                    "-isysroot",
                    "/usr/lib/arm-none-eabi",
                    "-iwithsysroot",
                    "/include"
                ],
                "projects":{
                    "OpenTCP-1.0.4":26173,
                    "bzip2-1.0.2":56984,
                    "cg_compiler_opensrc":100286,
                    "compiler":22020,
                    "flex-2.5.31":197553,
                    "jikespg-1.3":179490,
                    "jpeg-6b":119949,
                    "libmspack":57976,
                    "libpng-1.2.5":90889,
                    "lwip-0.5.3.preproc":116126,
                    "mpeg2dec-0.3.1":43564,
                    "mpgcut-1.1":12650,
                    "replaypc-0.4.0.preproc":80077,
                    "teem-1.6.0-src":875773,
                    "ttt-0.10.1.preproc":28988,
                    "unrarlib-0.4.0":11954,
                    "zlib-1.1.4":32086
                },
                "sum":2052538
            },
            "clang-trunk-cortex-m0-Oz":{
                "flags":[
                    "--target=arm-none-eabi",
                    "-Oz",
                    "-mcpu=cortex-m0",
                    "-mthumb",
                    "-isysroot",
                    "/usr/lib/arm-none-eabi",
                    "-iwithsysroot",
                    "/include"
                ],
                "projects":{
                    "OpenTCP-1.0.4":23931,
                    "bzip2-1.0.2":49104,
                    "cg_compiler_opensrc":97036,
                    "compiler":21188,
                    "flex-2.5.31":192173,
                    "jikespg-1.3":171386,
                    "jpeg-6b":112147,
                    "libmspack":56208,
                    "libpng-1.2.5":88215,
                    "lwip-0.5.3.preproc":116126,
                    "mpeg2dec-0.3.1":41790,
                    "mpgcut-1.1":7622,
                    "replaypc-0.4.0.preproc":80077,
                    "teem-1.6.0-src":867809,
                    "ttt-0.10.1.preproc":28988,
                    "unrarlib-0.4.0":11382,
                    "zlib-1.1.4":31860
                },
                "sum":1997042
            },
            "clang-trunk-cortex-m4-Os":{
                "flags":[
                    "--target=arm-none-eabi",
                    "-Os",
                    "-mcpu=cortex-m4",
                    "-mthumb",
                    "-isysroot",
                    "/usr/lib/arm-none-eabi",
                    "-iwithsysroot",
                    "/include"
                ],
                "projects":{
                    "OpenTCP-1.0.4":26901,
                    "bzip2-1.0.2":61830,
                    "cg_compiler_opensrc":103960,
                    "compiler":23142,
                    "flex-2.5.31":211549,
                    "jikespg-1.3":207536,
                    "jpeg-6b":118095,
                    "libmspack":60630,
                    "libpng-1.2.5":90705,
                    "lwip-0.5.3.preproc":116126,
                    "mpeg2dec-0.3.1":43706,
                    "mpgcut-1.1":14782,
                    "replaypc-0.4.0.preproc":80077,
                    "teem-1.6.0-src":950907,
                    "ttt-0.10.1.preproc":28988,
                    "unrarlib-0.4.0":13484,
                    "zlib-1.1.4":32190
                },
                "sum":2184608
            },
            "clang-trunk-cortex-m4-Oz":{
                "flags":[
                    "--target=arm-none-eabi",
                    "-Oz",
                    "-mcpu=cortex-m4",
                    "-mthumb",
                    "-isysroot",
                    "/usr/lib/arm-none-eabi",
                    "-iwithsysroot",
                    "/include"
                ],
                "projects":{
                    "OpenTCP-1.0.4":24019,
                    "bzip2-1.0.2":49608,
                    "cg_compiler_opensrc":95906,
                    "compiler":20804,
                    "flex-2.5.31":192413,
                    "jikespg-1.3":174414,
                    "jpeg-6b":107863,
                    "libmspack":55482,
                    "libpng-1.2.5":86047,
                    "lwip-0.5.3.preproc":116126,
                    "mpeg2dec-0.3.1":40424,
                    "mpgcut-1.1":8022,
                    "replaypc-0.4.0.preproc":80077,
                    "teem-1.6.0-src":918273,
                    "ttt-0.10.1.preproc":28988,
                    "unrarlib-0.4.0":11650,
                    "zlib-1.1.4":31228
                },
                "sum":2041344
            },
            "clang-trunk-native-Os":{
                "flags":[
                    "-Os"
                ],
                "projects":{
                    "OpenTCP-1.0.4":37239,
                    "bzip2-1.0.2":74609,
                    "cg_compiler_opensrc":141845,
                    "compiler":29403,
                    "flex-2.5.31":215317,
                    "jikespg-1.3":228729,
                    "jpeg-6b":160389,
                    "libmspack":76509,
                    "libpng-1.2.5":117681,
                    "lwip-0.5.3.preproc":116126,
                    "mpeg2dec-0.3.1":64806,
                    "mpgcut-1.1":12143,
                    "replaypc-0.4.0.preproc":80077,
                    "teem-1.6.0-src":1006396,
                    "ttt-0.10.1.preproc":28988,
                    "unrarlib-0.4.0":15259,
                    "zlib-1.1.4":45058
                },
                "sum":2450574
            },
            "clang-trunk-native-Oz":{
                "flags":[
                    "-Oz"
                ],
                "projects":{
                    "OpenTCP-1.0.4":35052,
                    "bzip2-1.0.2":64569,
                    "cg_compiler_opensrc":140369,
                    "compiler":28023,
                    "flex-2.5.31":212490,
                    "jikespg-1.3":224294,
                    "jpeg-6b":151966,
                    "libmspack":77008,
                    "libpng-1.2.5":115071,
                    "lwip-0.5.3.preproc":116126,
                    "mpeg2dec-0.3.1":53909,
                    "mpgcut-1.1":9669,
                    "replaypc-0.4.0.preproc":80077,
                    "teem-1.6.0-src":1006817,
                    "ttt-0.10.1.preproc":28988,
                    "unrarlib-0.4.0":14830,
                    "zlib-1.1.4":46032
                },
                "sum":2405290
            }
        },
        "324793":{
            "clang-trunk-cortex-m0-Os":{
                "flags":[
                    "--target=arm-none-eabi",
                    "-Os",
                    "-mcpu=cortex-m0",
                    "-mthumb",
                    "-isysroot",
                    "/usr/lib/arm-none-eabi",
                    "-iwithsysroot",
                    "/include"
                ],
                "projects":{
                    "OpenTCP-1.0.4":26173,
                    "bzip2-1.0.2":56984,
                    "cg_compiler_opensrc":100286,
                    "compiler":22020,
                    "flex-2.5.31":197553,
                    "jikespg-1.3":179490,
                    "jpeg-6b":119949,
                    "libmspack":57976,
                    "libpng-1.2.5":90889,
                    "lwip-0.5.3.preproc":116126,
                    "mpeg2dec-0.3.1":43564,
                    "mpgcut-1.1":12650,
                    "replaypc-0.4.0.preproc":80077,
                    "teem-1.6.0-src":875773,
                    "ttt-0.10.1.preproc":28988,
                    "unrarlib-0.4.0":11954,
                    "zlib-1.1.4":32086
                },
                "sum":2052538
            },
            "clang-trunk-cortex-m0-Oz":{
                "flags":[
                    "--target=arm-none-eabi",
                    "-Oz",
                    "-mcpu=cortex-m0",
                    "-mthumb",
                    "-isysroot",
                    "/usr/lib/arm-none-eabi",
                    "-iwithsysroot",
                    "/include"
                ],
                "projects":{
                    "OpenTCP-1.0.4":23931,
                    "bzip2-1.0.2":49104,
                    "cg_compiler_opensrc":97036,
                    "compiler":21188,
                    "flex-2.5.31":192173,
                    "jikespg-1.3":171386,
                    "jpeg-6b":112147,
                    "libmspack":56208,
                    "libpng-1.2.5":88215,
                    "lwip-0.5.3.preproc":116126,
                    "mpeg2dec-0.3.1":41790,
                    "mpgcut-1.1":7622,
                    "replaypc-0.4.0.preproc":80077,
                    "teem-1.6.0-src":867809,
                    "ttt-0.10.1.preproc":28988,
                    "unrarlib-0.4.0":11382,
                    "zlib-1.1.4":31860
                },
                "sum":1997042
            },
            "clang-trunk-cortex-m4-Os":{
                "flags":[
                    "--target=arm-none-eabi",
                    "-Os",
                    "-mcpu=cortex-m4",
                    "-mthumb",
                    "-isysroot",
                    "/usr/lib/arm-none-eabi",
                    "-iwithsysroot",
                    "/include"
                ],
                "projects":{
                    "OpenTCP-1.0.4":26901,
                    "bzip2-1.0.2":61830,
                    "cg_compiler_opensrc":103960,
                    "compiler":23142,
                    "flex-2.5.31":211549,
                    "jikespg-1.3":207536,
                    "jpeg-6b":118095,
                    "libmspack":60630,
                    "libpng-1.2.5":90705,
                    "lwip-0.5.3.preproc":116126,
                    "mpeg2dec-0.3.1":43706,
                    "mpgcut-1.1":14782,
                    "replaypc-0.4.0.preproc":80077,
                    "teem-1.6.0-src":950907,
                    "ttt-0.10.1.preproc":28988,
                    "unrarlib-0.4.0":13484,
                    "zlib-1.1.4":32190
                },
                "sum":2184608
            },
            "clang-trunk-cortex-m4-Oz":{
                "flags":[
                    "--target=arm-none-eabi",
                    "-Oz",
                    "-mcpu=cortex-m4",
                    "-mthumb",
                    "-isysroot",
                    "/usr/lib/arm-none-eabi",
                    "-iwithsysroot",
                    "/include"
                ],
                "projects":{
                    "OpenTCP-1.0.4":24019,
                    "bzip2-1.0.2":49608,
                    "cg_compiler_opensrc":95906,
                    "compiler":20804,
                    "flex-2.5.31":192413,
                    "jikespg-1.3":174414,
                    "jpeg-6b":107863,
                    "libmspack":55482,
                    "libpng-1.2.5":86047,
                    "lwip-0.5.3.preproc":116126,
                    "mpeg2dec-0.3.1":40424,
                    "mpgcut-1.1":8022,
                    "replaypc-0.4.0.preproc":80077,
                    "teem-1.6.0-src":918273,
                    "ttt-0.10.1.preproc":28988,
                    "unrarlib-0.4.0":11650,
                    "zlib-1.1.4":31228
                },
                "sum":2041344
            },
            "clang-trunk-native-Os":{
                "flags":[
                    "-Os"
                ],
                "projects":{
                    "OpenTCP-1.0.4":37239,
                    "bzip2-1.0.2":74609,
                    "cg_compiler_opensrc":141845,
                    "compiler":29403,
                    "flex-2.5.31":215317,
                    "jikespg-1.3":228729,
                    "jpeg-6b":160389,
                    "libmspack":76509,
                    "libpng-1.2.5":117681,
                    "lwip-0.5.3.preproc":116126,
                    "mpeg2dec-0.3.1":64806,
                    "mpgcut-1.1":12143,
                    "replaypc-0.4.0.preproc":80077,
                    "teem-1.6.0-src":1006396,
                    "ttt-0.10.1.preproc":28988,
                    "unrarlib-0.4.0":15259,
                    "zlib-1.1.4":45058
                },
                "sum":2450574
            },
            "clang-trunk-native-Oz":{
                "flags":[
                    "-Oz"
                ],
                "projects":{
                    "OpenTCP-1.0.4":35052,
                    "bzip2-1.0.2":64569,
                    "cg_compiler_opensrc":140369,
                    "compiler":28023,
                    "flex-2.5.31":212490,
                    "jikespg-1.3":224294,
                    "jpeg-6b":151966,
                    "libmspack":77008,
                    "libpng-1.2.5":115071,
                    "lwip-0.5.3.preproc":116126,
                    "mpeg2dec-0.3.1":53909,
                    "mpgcut-1.1":9669,
                    "replaypc-0.4.0.preproc":80077,
                    "teem-1.6.0-src":1006817,
                    "ttt-0.10.1.preproc":28988,
                    "unrarlib-0.4.0":14830,
                    "zlib-1.1.4":46032
                },
                "sum":2405290
            }
        },
        "324794":{
            "clang-trunk-cortex-m0-Os":{
                "flags":[
                    "--target=arm-none-eabi",
                    "-Os",
                    "-mcpu=cortex-m0",
                    "-mthumb",
                    "-isysroot",
                    "/usr/lib/arm-none-eabi",
                    "-iwithsysroot",
                    "/include"
                ],
                "projects":{
                    "OpenTCP-1.0.4":26173,
                    "bzip2-1.0.2":56984,
                    "cg_compiler_opensrc":100286,
                    "compiler":22020,
                    "flex-2.5.31":197553,
                    "jikespg-1.3":179490,
                    "jpeg-6b":119949,
                    "libmspack":57976,
                    "libpng-1.2.5":90889,
                    "lwip-0.5.3.preproc":116126,
                    "mpeg2dec-0.3.1":43564,
                    "mpgcut-1.1":12650,
                    "replaypc-0.4.0.preproc":80077,
                    "teem-1.6.0-src":875773,
                    "ttt-0.10.1.preproc":28988,
                    "unrarlib-0.4.0":11954,
                    "zlib-1.1.4":32086
                },
                "sum":2052538
            },
            "clang-trunk-cortex-m0-Oz":{
                "flags":[
                    "--target=arm-none-eabi",
                    "-Oz",
                    "-mcpu=cortex-m0",
                    "-mthumb",
                    "-isysroot",
                    "/usr/lib/arm-none-eabi",
                    "-iwithsysroot",
                    "/include"
                ],
                "projects":{
                    "OpenTCP-1.0.4":23931,
                    "bzip2-1.0.2":49104,
                    "cg_compiler_opensrc":97036,
                    "compiler":21188,
                    "flex-2.5.31":192173,
                    "jikespg-1.3":171386,
                    "jpeg-6b":112147,
                    "libmspack":56208,
                    "libpng-1.2.5":88215,
                    "lwip-0.5.3.preproc":116126,
                    "mpeg2dec-0.3.1":41790,
                    "mpgcut-1.1":7622,
                    "replaypc-0.4.0.preproc":80077,
                    "teem-1.6.0-src":867809,
                    "ttt-0.10.1.preproc":28988,
                    "unrarlib-0.4.0":11382,
                    "zlib-1.1.4":31860
                },
                "sum":1997042
            },
            "clang-trunk-cortex-m4-Os":{
                "flags":[
                    "--target=arm-none-eabi",
                    "-Os",
                    "-mcpu=cortex-m4",
                    "-mthumb",
                    "-isysroot",
                    "/usr/lib/arm-none-eabi",
                    "-iwithsysroot",
                    "/include"
                ],
                "projects":{
                    "OpenTCP-1.0.4":26901,
                    "bzip2-1.0.2":61830,
                    "cg_compiler_opensrc":103960,
                    "compiler":23142,
                    "flex-2.5.31":211549,
                    "jikespg-1.3":207536,
                    "jpeg-6b":118095,
                    "libmspack":60630,
                    "libpng-1.2.5":90705,
                    "lwip-0.5.3.preproc":116126,
                    "mpeg2dec-0.3.1":43706,
                    "mpgcut-1.1":14782,
                    "replaypc-0.4.0.preproc":80077,
                    "teem-1.6.0-src":950907,
                    "ttt-0.10.1.preproc":28988,
                    "unrarlib-0.4.0":13484,
                    "zlib-1.1.4":32190
                },
                "sum":2184608
            },
            "clang-trunk-cortex-m4-Oz":{
                "flags":[
                    "--target=arm-none-eabi",
                    "-Oz",
                    "-mcpu=cortex-m4",
                    "-mthumb",
                    "-isysroot",
                    "/usr/lib/arm-none-eabi",
                    "-iwithsysroot",
                    "/include"
                ],
                "projects":{
                    "OpenTCP-1.0.4":24019,
                    "bzip2-1.0.2":49608,
                    "cg_compiler_opensrc":95906,
                    "compiler":20804,
                    "flex-2.5.31":192413,
                    "jikespg-1.3":174414,
                    "jpeg-6b":107863,
                    "libmspack":55482,
                    "libpng-1.2.5":86047,
                    "lwip-0.5.3.preproc":116126,
                    "mpeg2dec-0.3.1":40424,
                    "mpgcut-1.1":8022,
                    "replaypc-0.4.0.preproc":80077,
                    "teem-1.6.0-src":918273,
                    "ttt-0.10.1.preproc":28988,
                    "unrarlib-0.4.0":11650,
                    "zlib-1.1.4":31228
                },
                "sum":2041344
            },
            "clang-trunk-native-Os":{
                "flags":[
                    "-Os"
                ],
                "projects":{
                    "OpenTCP-1.0.4":37239,
                    "bzip2-1.0.2":74609,
                    "cg_compiler_opensrc":141845,
                    "compiler":29403,
                    "flex-2.5.31":215317,
                    "jikespg-1.3":228729,
                    "jpeg-6b":160389,
                    "libmspack":76509,
                    "libpng-1.2.5":117681,
                    "lwip-0.5.3.preproc":116126,
                    "mpeg2dec-0.3.1":64806,
                    "mpgcut-1.1":12143,
                    "replaypc-0.4.0.preproc":80077,
                    "teem-1.6.0-src":1006396,
                    "ttt-0.10.1.preproc":28988,
                    "unrarlib-0.4.0":15259,
                    "zlib-1.1.4":45058
                },
                "sum":2450574
            },
            "clang-trunk-native-Oz":{
                "flags":[
                    "-Oz"
                ],
                "projects":{
                    "OpenTCP-1.0.4":35052,
                    "bzip2-1.0.2":64569,
                    "cg_compiler_opensrc":140369,
                    "compiler":28023,
                    "flex-2.5.31":212490,
                    "jikespg-1.3":224294,
                    "jpeg-6b":151966,
                    "libmspack":77008,
                    "libpng-1.2.5":115071,
                    "lwip-0.5.3.preproc":116126,
                    "mpeg2dec-0.3.1":53909,
                    "mpgcut-1.1":9669,
                    "replaypc-0.4.0.preproc":80077,
                    "teem-1.6.0-src":1006817,
                    "ttt-0.10.1.preproc":28988,
                    "unrarlib-0.4.0":14830,
                    "zlib-1.1.4":46032
                },
                "sum":2405290
            }
        },
        "324796":{
            "clang-trunk-cortex-m0-Os":{
                "flags":[
                    "--target=arm-none-eabi",
                    "-Os",
                    "-mcpu=cortex-m0",
                    "-mthumb",
                    "-isysroot",
                    "/usr/lib/arm-none-eabi",
                    "-iwithsysroot",
                    "/include"
                ],
                "projects":{
                    "OpenTCP-1.0.4":26173,
                    "bzip2-1.0.2":56984,
                    "cg_compiler_opensrc":100286,
                    "compiler":22020,
                    "flex-2.5.31":197553,
                    "jikespg-1.3":179490,
                    "jpeg-6b":119949,
                    "libmspack":57976,
                    "libpng-1.2.5":90889,
                    "lwip-0.5.3.preproc":116126,
                    "mpeg2dec-0.3.1":43564,
                    "mpgcut-1.1":12650,
                    "replaypc-0.4.0.preproc":80077,
                    "teem-1.6.0-src":875773,
                    "ttt-0.10.1.preproc":28988,
                    "unrarlib-0.4.0":11954,
                    "zlib-1.1.4":32086
                },
                "sum":2052538
            },
            "clang-trunk-cortex-m0-Oz":{
                "flags":[
                    "--target=arm-none-eabi",
                    "-Oz",
                    "-mcpu=cortex-m0",
                    "-mthumb",
                    "-isysroot",
                    "/usr/lib/arm-none-eabi",
                    "-iwithsysroot",
                    "/include"
                ],
                "projects":{
                    "OpenTCP-1.0.4":23931,
                    "bzip2-1.0.2":49104,
                    "cg_compiler_opensrc":97036,
                    "compiler":21188,
                    "flex-2.5.31":192173,
                    "jikespg-1.3":171386,
                    "jpeg-6b":112147,
                    "libmspack":56208,
                    "libpng-1.2.5":88215,
                    "lwip-0.5.3.preproc":116126,
                    "mpeg2dec-0.3.1":41790,
                    "mpgcut-1.1":7622,
                    "replaypc-0.4.0.preproc":80077,
                    "teem-1.6.0-src":867809,
                    "ttt-0.10.1.preproc":28988,
                    "unrarlib-0.4.0":11382,
                    "zlib-1.1.4":31860
                },
                "sum":1997042
            },
            "clang-trunk-cortex-m4-Os":{
                "flags":[
                    "--target=arm-none-eabi",
                    "-Os",
                    "-mcpu=cortex-m4",
                    "-mthumb",
                    "-isysroot",
                    "/usr/lib/arm-none-eabi",
                    "-iwithsysroot",
                    "/include"
                ],
                "projects":{
                    "OpenTCP-1.0.4":26901,
                    "bzip2-1.0.2":61830,
                    "cg_compiler_opensrc":103960,
                    "compiler":23142,
                    "flex-2.5.31":211549,
                    "jikespg-1.3":207536,
                    "jpeg-6b":118095,
                    "libmspack":60630,
                    "libpng-1.2.5":90705,
                    "lwip-0.5.3.preproc":116126,
                    "mpeg2dec-0.3.1":43706,
                    "mpgcut-1.1":14782,
                    "replaypc-0.4.0.preproc":80077,
                    "teem-1.6.0-src":950907,
                    "ttt-0.10.1.preproc":28988,
                    "unrarlib-0.4.0":13484,
                    "zlib-1.1.4":32190
                },
                "sum":2184608
            },
            "clang-trunk-cortex-m4-Oz":{
                "flags":[
                    "--target=arm-none-eabi",
                    "-Oz",
                    "-mcpu=cortex-m4",
                    "-mthumb",
                    "-isysroot",
                    "/usr/lib/arm-none-eabi",
                    "-iwithsysroot",
                    "/include"
                ],
                "projects":{
                    "OpenTCP-1.0.4":24019,
                    "bzip2-1.0.2":49608,
                    "cg_compiler_opensrc":95906,
                    "compiler":20804,
                    "flex-2.5.31":192413,
                    "jikespg-1.3":174414,
                    "jpeg-6b":107863,
                    "libmspack":55482,
                    "libpng-1.2.5":86047,
                    "lwip-0.5.3.preproc":116126,
                    "mpeg2dec-0.3.1":40424,
                    "mpgcut-1.1":8022,
                    "replaypc-0.4.0.preproc":80077,
                    "teem-1.6.0-src":918273,
                    "ttt-0.10.1.preproc":28988,
                    "unrarlib-0.4.0":11650,
                    "zlib-1.1.4":31228
                },
                "sum":2041344
            },
            "clang-trunk-native-Os":{
                "flags":[
                    "-Os"
                ],
                "projects":{
                    "OpenTCP-1.0.4":37239,
                    "bzip2-1.0.2":74609,
                    "cg_compiler_opensrc":141845,
                    "compiler":29403,
                    "flex-2.5.31":215317,
                    "jikespg-1.3":228729,
                    "jpeg-6b":160389,
                    "libmspack":76509,
                    "libpng-1.2.5":117681,
                    "lwip-0.5.3.preproc":116126,
                    "mpeg2dec-0.3.1":64806,
                    "mpgcut-1.1":12143,
                    "replaypc-0.4.0.preproc":80077,
                    "teem-1.6.0-src":1006396,
                    "ttt-0.10.1.preproc":28988,
                    "unrarlib-0.4.0":15259,
                    "zlib-1.1.4":45058
                },
                "sum":2450574
            },
            "clang-trunk-native-Oz":{
                "flags":[
                    "-Oz"
                ],
                "projects":{
                    "OpenTCP-1.0.4":35052,
                    "bzip2-1.0.2":64569,
                    "cg_compiler_opensrc":140369,
                    "compiler":28023,
                    "flex-2.5.31":212490,
                    "jikespg-1.3":224294,
                    "jpeg-6b":151966,
                    "libmspack":77008,
                    "libpng-1.2.5":115071,
                    "lwip-0.5.3.preproc":116126,
                    "mpeg2dec-0.3.1":53909,
                    "mpgcut-1.1":9669,
                    "replaypc-0.4.0.preproc":80077,
                    "teem-1.6.0-src":1006817,
                    "ttt-0.10.1.preproc":28988,
                    "unrarlib-0.4.0":14830,
                    "zlib-1.1.4":46032
                },
                "sum":2405290
            }
        },
        "324797":{
            "clang-trunk-cortex-m0-Os":{
                "flags":[
                    "--target=arm-none-eabi",
                    "-Os",
                    "-mcpu=cortex-m0",
                    "-mthumb",
                    "-isysroot",
                    "/usr/lib/arm-none-eabi",
                    "-iwithsysroot",
                    "/include"
                ],
                "projects":{
                    "OpenTCP-1.0.4":26173,
                    "bzip2-1.0.2":56984,
                    "cg_compiler_opensrc":100286,
                    "compiler":22020,
                    "flex-2.5.31":197553,
                    "jikespg-1.3":179490,
                    "jpeg-6b":119949,
                    "libmspack":57976,
                    "libpng-1.2.5":90889,
                    "lwip-0.5.3.preproc":116126,
                    "mpeg2dec-0.3.1":43564,
                    "mpgcut-1.1":12650,
                    "replaypc-0.4.0.preproc":80077,
                    "teem-1.6.0-src":875773,
                    "ttt-0.10.1.preproc":28988,
                    "unrarlib-0.4.0":11954,
                    "zlib-1.1.4":32086
                },
                "sum":2052538
            },
            "clang-trunk-cortex-m0-Oz":{
                "flags":[
                    "--target=arm-none-eabi",
                    "-Oz",
                    "-mcpu=cortex-m0",
                    "-mthumb",
                    "-isysroot",
                    "/usr/lib/arm-none-eabi",
                    "-iwithsysroot",
                    "/include"
                ],
                "projects":{
                    "OpenTCP-1.0.4":23931,
                    "bzip2-1.0.2":49104,
                    "cg_compiler_opensrc":97036,
                    "compiler":21188,
                    "flex-2.5.31":192173,
                    "jikespg-1.3":171386,
                    "jpeg-6b":112147,
                    "libmspack":56208,
                    "libpng-1.2.5":88215,
                    "lwip-0.5.3.preproc":116126,
                    "mpeg2dec-0.3.1":41790,
                    "mpgcut-1.1":7622,
                    "replaypc-0.4.0.preproc":80077,
                    "teem-1.6.0-src":867809,
                    "ttt-0.10.1.preproc":28988,
                    "unrarlib-0.4.0":11382,
                    "zlib-1.1.4":31860
                },
                "sum":1997042
            },
            "clang-trunk-cortex-m4-Os":{
                "flags":[
                    "--target=arm-none-eabi",
                    "-Os",
                    "-mcpu=cortex-m4",
                    "-mthumb",
                    "-isysroot",
                    "/usr/lib/arm-none-eabi",
                    "-iwithsysroot",
                    "/include"
                ],
                "projects":{
                    "OpenTCP-1.0.4":26901,
                    "bzip2-1.0.2":61830,
                    "cg_compiler_opensrc":103960,
                    "compiler":23142,
                    "flex-2.5.31":211549,
                    "jikespg-1.3":207536,
                    "jpeg-6b":118095,
                    "libmspack":60630,
                    "libpng-1.2.5":90705,
                    "lwip-0.5.3.preproc":116126,
                    "mpeg2dec-0.3.1":43706,
                    "mpgcut-1.1":14782,
                    "replaypc-0.4.0.preproc":80077,
                    "teem-1.6.0-src":950907,
                    "ttt-0.10.1.preproc":28988,
                    "unrarlib-0.4.0":13484,
                    "zlib-1.1.4":32190
                },
                "sum":2184608
            },
            "clang-trunk-cortex-m4-Oz":{
                "flags":[
                    "--target=arm-none-eabi",
                    "-Oz",
                    "-mcpu=cortex-m4",
                    "-mthumb",
                    "-isysroot",
                    "/usr/lib/arm-none-eabi",
                    "-iwithsysroot",
                    "/include"
                ],
                "projects":{
                    "OpenTCP-1.0.4":24019,
                    "bzip2-1.0.2":49608,
                    "cg_compiler_opensrc":95906,
                    "compiler":20804,
                    "flex-2.5.31":192413,
                    "jikespg-1.3":174414,
                    "jpeg-6b":107863,
                    "libmspack":55482,
                    "libpng-1.2.5":86047,
                    "lwip-0.5.3.preproc":116126,
                    "mpeg2dec-0.3.1":40424,
                    "mpgcut-1.1":8022,
                    "replaypc-0.4.0.preproc":80077,
                    "teem-1.6.0-src":918273,
                    "ttt-0.10.1.preproc":28988,
                    "unrarlib-0.4.0":11650,
                    "zlib-1.1.4":31228
                },
                "sum":2041344
            },
            "clang-trunk-native-Os":{
                "flags":[
                    "-Os"
                ],
                "projects":{
                    "OpenTCP-1.0.4":37239,
                    "bzip2-1.0.2":74609,
                    "cg_compiler_opensrc":141845,
                    "compiler":29403,
                    "flex-2.5.31":215317,
                    "jikespg-1.3":228729,
                    "jpeg-6b":160389,
                    "libmspack":76509,
                    "libpng-1.2.5":117681,
                    "lwip-0.5.3.preproc":116126,
                    "mpeg2dec-0.3.1":64806,
                    "mpgcut-1.1":12143,
                    "replaypc-0.4.0.preproc":80077,
                    "teem-1.6.0-src":1006396,
                    "ttt-0.10.1.preproc":28988,
                    "unrarlib-0.4.0":15259,
                    "zlib-1.1.4":45058
                },
                "sum":2450574
            },
            "clang-trunk-native-Oz":{
                "flags":[
                    "-Oz"
                ],
                "projects":{
                    "OpenTCP-1.0.4":35052,
                    "bzip2-1.0.2":64569,
                    "cg_compiler_opensrc":140369,
                    "compiler":28023,
                    "flex-2.5.31":212490,
                    "jikespg-1.3":224294,
                    "jpeg-6b":151966,
                    "libmspack":77008,
                    "libpng-1.2.5":115071,
                    "lwip-0.5.3.preproc":116126,
                    "mpeg2dec-0.3.1":53909,
                    "mpgcut-1.1":9669,
                    "replaypc-0.4.0.preproc":80077,
                    "teem-1.6.0-src":1006817,
                    "ttt-0.10.1.preproc":28988,
                    "unrarlib-0.4.0":14830,
                    "zlib-1.1.4":46032
                },
                "sum":2405290
            }
        },
        "324802":{
            "clang-trunk-cortex-m0-Os":{
                "flags":[
                    "--target=arm-none-eabi",
                    "-Os",
                    "-mcpu=cortex-m0",
                    "-mthumb",
                    "-isysroot",
                    "/usr/lib/arm-none-eabi",
                    "-iwithsysroot",
                    "/include"
                ],
                "projects":{
                    "OpenTCP-1.0.4":26173,
                    "bzip2-1.0.2":56984,
                    "cg_compiler_opensrc":100286,
                    "compiler":22020,
                    "flex-2.5.31":197553,
                    "jikespg-1.3":179490,
                    "jpeg-6b":119949,
                    "libmspack":57976,
                    "libpng-1.2.5":90889,
                    "lwip-0.5.3.preproc":116126,
                    "mpeg2dec-0.3.1":43564,
                    "mpgcut-1.1":12650,
                    "replaypc-0.4.0.preproc":80077,
                    "teem-1.6.0-src":875773,
                    "ttt-0.10.1.preproc":28988,
                    "unrarlib-0.4.0":11954,
                    "zlib-1.1.4":32086
                },
                "sum":2052538
            },
            "clang-trunk-cortex-m0-Oz":{
                "flags":[
                    "--target=arm-none-eabi",
                    "-Oz",
                    "-mcpu=cortex-m0",
                    "-mthumb",
                    "-isysroot",
                    "/usr/lib/arm-none-eabi",
                    "-iwithsysroot",
                    "/include"
                ],
                "projects":{
                    "OpenTCP-1.0.4":23931,
                    "bzip2-1.0.2":49104,
                    "cg_compiler_opensrc":97036,
                    "compiler":21188,
                    "flex-2.5.31":192173,
                    "jikespg-1.3":171386,
                    "jpeg-6b":112147,
                    "libmspack":56208,
                    "libpng-1.2.5":88215,
                    "lwip-0.5.3.preproc":116126,
                    "mpeg2dec-0.3.1":41790,
                    "mpgcut-1.1":7622,
                    "replaypc-0.4.0.preproc":80077,
                    "teem-1.6.0-src":867809,
                    "ttt-0.10.1.preproc":28988,
                    "unrarlib-0.4.0":11382,
                    "zlib-1.1.4":31860
                },
                "sum":1997042
            },
            "clang-trunk-cortex-m4-Os":{
                "flags":[
                    "--target=arm-none-eabi",
                    "-Os",
                    "-mcpu=cortex-m4",
                    "-mthumb",
                    "-isysroot",
                    "/usr/lib/arm-none-eabi",
                    "-iwithsysroot",
                    "/include"
                ],
                "projects":{
                    "OpenTCP-1.0.4":26901,
                    "bzip2-1.0.2":61830,
                    "cg_compiler_opensrc":103960,
                    "compiler":23142,
                    "flex-2.5.31":211549,
                    "jikespg-1.3":207536,
                    "jpeg-6b":118095,
                    "libmspack":60630,
                    "libpng-1.2.5":90705,
                    "lwip-0.5.3.preproc":116126,
                    "mpeg2dec-0.3.1":43706,
                    "mpgcut-1.1":14782,
                    "replaypc-0.4.0.preproc":80077,
                    "teem-1.6.0-src":950907,
                    "ttt-0.10.1.preproc":28988,
                    "unrarlib-0.4.0":13484,
                    "zlib-1.1.4":32190
                },
                "sum":2184608
            },
            "clang-trunk-cortex-m4-Oz":{
                "flags":[
                    "--target=arm-none-eabi",
                    "-Oz",
                    "-mcpu=cortex-m4",
                    "-mthumb",
                    "-isysroot",
                    "/usr/lib/arm-none-eabi",
                    "-iwithsysroot",
                    "/include"
                ],
                "projects":{
                    "OpenTCP-1.0.4":24019,
                    "bzip2-1.0.2":49608,
                    "cg_compiler_opensrc":95906,
                    "compiler":20804,
                    "flex-2.5.31":192413,
                    "jikespg-1.3":174414,
                    "jpeg-6b":107863,
                    "libmspack":55482,
                    "libpng-1.2.5":86047,
                    "lwip-0.5.3.preproc":116126,
                    "mpeg2dec-0.3.1":40424,
                    "mpgcut-1.1":8022,
                    "replaypc-0.4.0.preproc":80077,
                    "teem-1.6.0-src":918273,
                    "ttt-0.10.1.preproc":28988,
                    "unrarlib-0.4.0":11650,
                    "zlib-1.1.4":31228
                },
                "sum":2041344
            },
            "clang-trunk-native-Os":{
                "flags":[
                    "-Os"
                ],
                "projects":{
                    "OpenTCP-1.0.4":37239,
                    "bzip2-1.0.2":74609,
                    "cg_compiler_opensrc":141845,
                    "compiler":29403,
                    "flex-2.5.31":215317,
                    "jikespg-1.3":228729,
                    "jpeg-6b":160389,
                    "libmspack":76509,
                    "libpng-1.2.5":117681,
                    "lwip-0.5.3.preproc":116126,
                    "mpeg2dec-0.3.1":64806,
                    "mpgcut-1.1":12143,
                    "replaypc-0.4.0.preproc":80077,
                    "teem-1.6.0-src":1006396,
                    "ttt-0.10.1.preproc":28988,
                    "unrarlib-0.4.0":15259,
                    "zlib-1.1.4":45058
                },
                "sum":2450574
            },
            "clang-trunk-native-Oz":{
                "flags":[
                    "-Oz"
                ],
                "projects":{
                    "OpenTCP-1.0.4":35052,
                    "bzip2-1.0.2":64569,
                    "cg_compiler_opensrc":140369,
                    "compiler":28023,
                    "flex-2.5.31":212490,
                    "jikespg-1.3":224294,
                    "jpeg-6b":151966,
                    "libmspack":77008,
                    "libpng-1.2.5":115071,
                    "lwip-0.5.3.preproc":116126,
                    "mpeg2dec-0.3.1":53909,
                    "mpgcut-1.1":9669,
                    "replaypc-0.4.0.preproc":80077,
                    "teem-1.6.0-src":1006817,
                    "ttt-0.10.1.preproc":28988,
                    "unrarlib-0.4.0":14830,
                    "zlib-1.1.4":46032
                },
                "sum":2405290
            }
        }
    }
}